Workbook

Sheet Leia-me
A1: AtlasPen — auditoria por amostra: fichas e apuração
A2: Protocolo: AUDITORIA.md · versão auditada: commit 26742210c50e5ccdebfbd99b68784fa4ac70333d · amostra gerada em 2026-09-28
A3: 100 fichas para o Revisor A; 20 delas (em amarelo) também para o Revisor B, que não vê a ficha de A.
A5: Como preencher
A6: 1. Abra o link do compilado e leia o dispositivo indicado — o caput e os parágrafos que ele cita. Não consulte o site do AtlasPen: a ficha é cega de propósito, e ver o valor publicado induz a confirmá-lo.
A7: 2. Preencha os nove campos com o que A LEI diz. Pena mínima e máxima em MESES inteiros (1 ano = 12; 2 anos e 6 meses = 30; se a lei não fixa mínimo, escreva 0). Onde há lista suspensa, escolha um valor.
A8: 3. 'Hediondo' pede o rol do art. 1º da Lei 8.072/90, inclusive equiparados (CF, art. 5º, XLIII). 'Violência' e 'grave ameaça' são a violência DOLOSA contra pessoa e a ameaça como meio ou núcleo do tipo. 'Elemento subjetivo' segue a régua do projeto: doloso, culposo, preterdoloso, ou qualificado pelo resultado.
A9: 4. Quando o compilado não permitir decidir um campo, ou permitir mais de uma leitura, NÃO chute: escreva na coluna 'ressalvas' no formato campo: fonte insuficiente — motivo ou campo: juízo discutível — qual leitura e por quê. Uma ressalva por linha.
A10: 5. Anote o tempo gasto na ficha, em minutos. Serve para calibrar a fase 2 do protocolo.
A11: 6. Só DEPOIS de preencher a aba 'Fichas', abra 'Nomes e vigência': lá estão o nome publicado e a vigência, para você dizer se conferem com o que leu.
A12: 7. Linha destacada em amarelo está na subamostra de dupla conferência: se houver segunda pessoa, ela lê só essas, na aba Revisor B, sem ver a ficha da primeira.
A14: O que acontece depois
... A20: Nada aqui é lido pelo AtlasPen automaticamente: a apuração de referência é o scripts/auditoria/apurar.py, que dá os mesmos números. A planilha existe para que a conferência se veja enquanto se faz.

Sheet Revisor A
A1: id | B1: diploma | C1: dispositivo | D1: link do compilado | E1: dupla | F1: pena mínima (meses) | G1: ressalva | H1: pena máxima (meses) | I1: ressalva | J1: espécie de pena | K1: ressalva | L1: hediondo | M1: ressalva | N1: violência | O1: ressalva | P1: grave ameaça | Q1: ressalva | R1: elemento subjetivo | S1: ressalva | T1: admite tentativa | U1: ressalva | V1: ação penal | W1: ressalva | X1: tempo (min) | Y1: observações | Z1: nome publicado | AA1: vigente (publicado) | AB1: nome confere? | AC1: vigência confere?
A2: 165 | B2: CP | C2: Art. 211 | D2: https://www.planalto.gov.br/ccivil_03/decreto-lei/del2848compilado.htm | E2: sim | Z2: Destruição, subtração ou ocultação de cadáver | AA2: Sim
A3: 1335 | B3: CP | C3: Art. 254 (no caso de culpa) | D3: https://www.planalto.gov.br/ccivil_03/decreto-lei/del2848compilado.htm | E3: sim | Z3: Inundação — modalidade culposa | AA3: Sim
A4: 172 | B4: CP | C4: Art. 235 | D4: https://www.planalto.gov.br/ccivil_03/decreto-lei/del2848compilado.htm | E4: sim | Z4: Bigamia | AA4: Sim
A5: 994 | B5: CP | C5: Art. 162, caput | D5: https://www.planalto.gov.br/ccivil_03/decreto-lei/del2848compilado.htm | E5: sim | Z5: Alteração de marca ou sinal indicativo de propriedade de gado ou rebanho | AA5: Sim
A6: 70 | B6: CP | C6: Art. 148, §1º | D6: https://www.planalto.gov.br/ccivil_03/decreto-lei/del2848compilado.htm | E6: sim | Z6: Sequestro qualificado (fins libidinosos, menor de 18, maus-tratos, mais de 15 dias) | AA6: Sim
A7: 66 | B7: CP | C7: Art. 147 | D7: https://www.planalto.gov.br/ccivil_03/decreto-lei/del2848compilado.htm | E7: sim | Z7: Ameaça | AA7: Sim
A8: 280 | B8: CP | C8: Art. 342 | D8: https://www.planalto.gov.br/ccivil_03/decreto-lei/del2848compilado.htm | Z8: Falso testemunho ou falsa perícia | AA8: Sim
A9: 231 | B9: CP | C9: Art. 297 | D9: https://www.planalto.gov.br/ccivil_03/decreto-lei/del2848compilado.htm | Z9: Falsificação de documento público | AA9: Sim
A10: 1379 | B10: CP | C10: Art. 348, §1º | D10: https://www.planalto.gov.br/ccivil_03/decreto-lei/del2848compilado.htm | Z10: Favorecimento pessoal — Se ao crime não é cominada pena de reclusão | AA10: Sim
A11: 153 | B11: CP | C11: Art. 199 | D11: https://www.planalto.gov.br/ccivil_03/decreto-lei/del2848compilado.htm | Z11: Atentado contra a liberdade de associação | AA11: Sim
A12: 275 | B12: CP | C12: Art. 337-B | D12: https://www.planalto.gov.br/ccivil_03/decreto-lei/del2848compilado.htm | Z12: Corrupção ativa em transação comercial internacional | AA12: Sim
A13: 1375 | B13: CP | C13: Art. 337-M | D13: https://www.planalto.gov.br/ccivil_03/decreto-lei/del2848compilado.htm | Z13: Contratação inidônea | AA13: Sim
A14: 186 | B14: CP | C14: Art. 250, §2º | D14: https://www.planalto.gov.br/ccivil_03/decreto-lei/del2848compilado.htm | Z14: Incêndio culposo | AA14: Sim
A15: 49 | B15: CP | C15: Art. 133, §2º | D15: https://www.planalto.gov.br/ccivil_03/decreto-lei/del2848compilado.htm | Z15: Abandono de incapaz com resultado morte | AA15: Sim
A16: 213 | B16: CP | C16: Art. 278 | D16: https://www.planalto.gov.br/ccivil_03/decreto-lei/del2848compilado.htm | Z16: Outras substâncias nocivas à saúde pública | AA16: Sim
A17: 151 | B17: CP | C17: Art. 197, I | D17: https://www.planalto.gov.br/ccivil_03/decreto-lei/del2848compilado.htm | Z17: Atentado contra a liberdade de trabalho — profissão ou trabalho | AA17: Sim
A18: 1338 | B18: CP | C18: Art. 134, §1º | D18: https://www.planalto.gov.br/ccivil_03/decreto-lei/del2848compilado.htm | Z18: Exposição ou abandono de recém-nascido — lesão grave | AA18: Sim
A19: 294 | B19: CP | C19: Art. 356 | D19: https://www.planalto.gov.br/ccivil_03/decreto-lei/del2848compilado.htm | Z19: Sonegação de papel ou objeto de valor probatório por advogado ou procurador | AA19: Sim
... A35: 12 | B35: CP | C35: Art. 121, §4º, 1ª parte | D35: https://www.planalto.gov.br/ccivil_03/decreto-lei/del2848compilado.htm | Z35: Homicídio culposo com aumento de 1/3 (inobservância de regra técnica) | AA35: Sim
A36: 706 | B36: CPM (DL 1.001/69) | C36: Art. 291, caput | D36: https://www.planalto.gov.br/ccivil_03/decreto-lei/del1001compilado.htm | E36: sim | Z36: Receita ilegal | AA36: Sim
A37: 1196 | B37: CPM (DL 1.001/69) | C37: Art. 326, caput | D37: https://www.planalto.gov.br/ccivil_03/decreto-lei/del1001compilado.htm | E37: sim | Z37: Violação de sigilo funcional | AA37: Sim
A38: 1108 | B38: CPM (DL 1.001/69) | C38: Art. 235, caput | D38: https://www.planalto.gov.br/ccivil_03/decreto-lei/del1001compilado.htm | E38: sim | Z38: Ato de libidinagem | AA38: Sim
A39: 1050 | B39: CPM (DL 1.001/69) | C39: Art. 172, caput | D39: https://www.planalto.gov.br/ccivil_03/decreto-lei/del1001compilado.htm | E39: sim | Z39: Uso indevido de uniforme, distintivo ou insígnia militar por qualquer pessoa | AA39: Sim
A40: 1383 | B40: CPM (DL 1.001/69) | C40: Art. 182, caput (aos cabeças) | D40: https://www.planalto.gov.br/ccivil_03/decreto-lei/del1001compilado.htm | Z40: Amotinamento (cabeça) | AA40: Sim
A41: 1026 | B41: CPM (DL 1.001/69) | C41: Art. 145, §1º | D41: https://www.planalto.gov.br/ccivil_03/decreto-lei/del1001compilado.htm | Z41: Turbação de objeto ou documento — comprometimento da segurança ou eficiência bélica | AA41: Sim
A42: 1084 | B42: CPM (DL 1.001/69) | C42: Art. 210, caput | D42: https://www.planalto.gov.br/ccivil_03/decreto-lei/del1001compilado.htm | Z42: Lesão culposa | AA42: Sim
A43: 1033 | B43: CPM (DL 1.001/69) | C43: Art. 151, caput | D43: https://www.planalto.gov.br/ccivil_03/decreto-lei/del1001compilado.htm | Z43: Omissão de lealdade militar | AA43: Sim
A44: 1182 | B44: CPM (DL 1.001/69) | C44: Art. 310, caput | D44: https://www.planalto.gov.br/ccivil_03/decreto-lei/del1001compilado.htm | Z44: Participação ilícita | AA44: Sim
A45: 1273 | B45: CPM (DL 1.001/69) | C45: Art. 393, caput | D45: https://www.planalto.gov.br/ccivil_03/decreto-lei/del1001compilado.htm | Z45: Falta de apresentação | AA45: Sim
A46: 702 | B46: CPM (DL 1.001/69) | C46: Art. 248, caput | D46: https://www.planalto.gov.br/ccivil_03/decreto-lei/del1001compilado.htm | Z46: Apropriação indébita simples | AA46: Sim
A47: 1121 | B47: CPM (DL 1.001/69) | C47: Art. 254, caput | D47: https://www.planalto.gov.br/ccivil_03/decreto-lei/del1001compilado.htm | Z47: Receptação | AA47: Sim
A48: 710 | B48: CPM (DL 1.001/69) | C48: Art. 309, caput | D48: https://www.planalto.gov.br/ccivil_03/decreto-lei/del1001compilado.htm | Z48: Corrupção ativa | AA48: Sim
A49: 707 | B49: CPM (DL 1.001/69) | C49: Art. 298, caput | D49: https://www.planalto.gov.br/ccivil_03/decreto-lei/del1001compilado.htm | Z49: Desacato a superior | AA49: Sim
A50: 1269 | B50: CPM (DL 1.001/69) | C50: Art. 389, par. único | D50: https://www.planalto.gov.br/ccivil_03/decreto-lei/del1001compilado.htm | Z50: Violência contra superior ou militar de serviço — com arma, em presença do inimigo | AA50: Sim
A51: 1070 | B51: CPM (DL 1.001/69) | C51: Art. 191, caput | D51: https://www.planalto.gov.br/ccivil_03/decreto-lei/del1001compilado.htm | Z51: Concêrto para deserção | AA51: Sim
... A55: 675 | B55: CPM (DL 1.001/69) | C55: Art. 136, caput | D55: https://www.planalto.gov.br/ccivil_03/decreto-lei/del1001compilado.htm | Z55: Hostilidade contra país estrangeiro | AA55: Sim
A56: 1437 | B56: CPM (DL 1.001/69) | C56: Art. 404 c/c art. 240, §5º | D56: https://www.planalto.gov.br/ccivil_03/decreto-lei/del1001compilado.htm | E56: sim | Z56: Furto qualificado — coisa pertencente à Fazenda Pública (tempo de guerra) | AA56: Sim
A57: 1445 | B57: CPM (DL 1.001/69) | C57: Art. 405 c/c art. 243, §1º | D57: https://www.planalto.gov.br/ccivil_03/decreto-lei/del1001compilado.htm | Z57: Extorsão qualificada (tempo de guerra) | AA57: Sim
A58: 1439 | B58: CPM (DL 1.001/69) | C58: Art. 404 c/c art. 240, §6º-A | D58: https://www.planalto.gov.br/ccivil_03/decreto-lei/del1001compilado.htm | Z58: Furto qualificado — material de uso restrito militar (tempo de guerra) | AA58: Sim
A59: 1435 | B59: CPM (DL 1.001/69) | C59: Art. 391 c/c art. 192 | D59: https://www.planalto.gov.br/ccivil_03/decreto-lei/del1001compilado.htm | Z59: Deserção por evasão ou fuga (tempo de guerra) | AA59: Sim
A60: 1433 | B60: CPM (DL 1.001/69) | C60: Art. 391 c/c art. 191, I | D60: https://www.planalto.gov.br/ccivil_03/decreto-lei/del1001compilado.htm | Z60: Concerto para deserção não consumada (tempo de guerra) | AA60: Sim
A61: 1526 | B61: CPM (DL 1.001/69) | C61: Art. 244, §2º | D61: https://www.planalto.gov.br/ccivil_03/decreto-lei/del1001compilado.htm | Z61: Extorsão mediante sequestro — grave sofrimento físico ou moral (tempo de paz) | AA61: Sim
A62: 1431 | B62: CPM (DL 1.001/69) | C62: Art. 391 c/c art. 190, §2º | D62: https://www.planalto.gov.br/ccivil_03/decreto-lei/del1001compilado.htm | Z62: Deserção especial — apresentação em mais de 5 e até 8 dias (tempo de guerra) | AA62: Sim
A63: 1454 | B63: CPM (DL 1.001/69) | C63: Art. 243, §2º | D63: https://www.planalto.gov.br/ccivil_03/decreto-lei/del1001compilado.htm | Z63: Extorsão qualificada pela morte (tempo de paz) | AA63: Sim
A64: 1527 | B64: CPM (DL 1.001/69) | C64: Art. 292, §1º | D64: https://www.planalto.gov.br/ccivil_03/decreto-lei/del1001compilado.htm | Z64: Epidemia com resultado morte | AA64: Sim
A65: 1429 | B65: CPM (DL 1.001/69) | C65: Art. 391 c/c art. 190, caput | D65: https://www.planalto.gov.br/ccivil_03/decreto-lei/del1001compilado.htm | Z65: Deserção especial (tempo de guerra) | AA65: Sim
A66: 1430 | B66: CPM (DL 1.001/69) | C66: Art. 391 c/c art. 190, §1º | D66: https://www.planalto.gov.br/ccivil_03/decreto-lei/del1001compilado.htm | Z66: Deserção especial — apresentação em mais de 24 horas e até 5 dias (tempo de guerra) | AA66: Sim
A67: 1298 | B67: Lei 1.521/51 | C67: Art. 4º, b | D67: https://www.planalto.gov.br/ccivil_03/leis/l1521.htm | E67: sim | Z67: Usura real | AA67: Sim
A68: 941 | B68: CE (Lei 4.737/65) | C68: Art. 335 | D68: https://www.planalto.gov.br/ccivil_03/leis/l4737compilado.htm | E68: sim | Z68: Propaganda eleitoral em língua estrangeira | AA68: Sim
A69: 786 | B69: CE (Lei 4.737/65) | C69: Art. 324 | D69: https://www.planalto.gov.br/ccivil_03/leis/l4737compilado.htm | E69: sim | Z69: Calúnia eleitoral | AA69: Sim
A70: 660 | B70: Lei 8.137/90 | C70: Art. 1º, II | D70: https://www.planalto.gov.br/ccivil_03/leis/l8137.htm | E70: sim | Z70: Supressão ou redução de tributo — fraude à fiscalização tributária | AA70: Sim
A71: 884 | B71: Lei 6.538/78 | C71: Art. 40 | D71: https://www.planalto.gov.br/ccivil_03/leis/l6538.htm | E71: sim | Z71: Violação de correspondência | AA71: Sim
A72: 846 | B72: LCP (DL 3.688/41) | C72: Art. 55 | D72: https://www.planalto.gov.br/ccivil_03/decreto-lei/del3688.htm | E72: sim | Z72: Impressão de bilhetes, listas de sorteio, avisos ou cartazes de loteria onde ela não possa legalmente circular | AA72: Sim
A73: 433 | B73: Lei 13.869/19 | C73: Art. 21 | D73: https://www.planalto.gov.br/ccivil_03/_ato2019-2022/2019/lei/l13869.htm | E73: sim | Z73: Manutenção de presos de sexos diferentes na mesma cela ou espaço de confinamento | AA73: Sim
A74: 395 | B74: Lei 8.137/90 | C74: Art. 1º | D74: https://www.planalto.gov.br/ccivil_03/leis/l8137.htm | Z74: Sonegação fiscal material (suprimir/reduzir tributo mediante conduta comissiva) | AA74: Sim
A75: 645 | B75: Lei 11.105/05 | C75: Art. 25 | D75: https://www.planalto.gov.br/ccivil_03/_ato2004-2006/2005/lei/l11105.htm | Z75: Engenharia genética em célula germinal humana, zigoto ou embrião humano | AA75: Sim
A76: 914 | B76: DL 6.259/44 | C76: Art. 49 | D76: https://www.planalto.gov.br/ccivil_03/decreto-lei/1937-1946/del6259.htm | Z76: Exibição ou guarda de listas de sorteio de loteria estrangeira ou de loteria estadual fora do território respectivo | AA76: Sim
A77: 844 | B77: LCP (DL 3.688/41) | C77: Art. 53 | D77: https://www.planalto.gov.br/ccivil_03/decreto-lei/del3688.htm | Z77: Loteria estadual | AA77: Sim
A78: 1007 | B78: Lei 1.521/51 | C78: Art. 4º, a | D78: https://www.planalto.gov.br/ccivil_03/leis/l1521.htm | Z78: Usura pecuniária (cobrar juros, comissões ou descontos acima da taxa legal) | AA78: Sim
A79: 391 | B79: Lei 12.850/13 | C79: Art. 21 | D79: https://www.planalto.gov.br/ccivil_03/_ato2011-2014/2013/lei/l12850.htm | Z79: Recusa ou omissão de dados requisitados na investigação ou no processo | AA79: Sim
A80: 967 | B80: Lei 10.741/03 | C80: Art. 105 | D80: https://www.planalto.gov.br/ccivil_03/leis/2003/l10.741.htm | Z80: Exibição de informações ou imagens depreciativas da pessoa idosa | AA80: Sim
A81: 1005 | B81: Lei 13.869/19 | C81: Art. 32 | D81: https://www.planalto.gov.br/ccivil_03/_ato2019-2022/2019/lei/l13869.htm | Z81: Negativa de acesso aos autos ao interessado, ao defensor ou ao advogado | AA81: Sim
A82: 420 | B82: Lei 7.716/89 | C82: Art. 12 | D82: https://www.planalto.gov.br/ccivil_03/leis/l7716.htm | Z82: Impedimento de acesso ou uso de transportes públicos | AA82: Sim
A83: 1427 | B83: Lei 9.605/98 | C83: Art. 68, parágrafo único (culposa) | D83: https://www.planalto.gov.br/ccivil_03/leis/l9605.htm | Z83: Descumprimento de obrigação de relevante interesse ambiental — modalidade culposa | AA83: Sim
A84: 362 | B84: Lei 9.605/98 | C84: Art. 45 | D84: https://www.planalto.gov.br/ccivil_03/leis/l9605.htm | Z84: Cortar ou transformar em carvão madeira de lei protegida sem autorização | AA84: Sim
A85: 532 | B85: Lei 9.504/97 | C85: Art. 33, §4º | D85: https://www.planalto.gov.br/ccivil_03/leis/l9504.htm | Z85: Divulgação de pesquisa eleitoral fraudulenta | AA85: Sim
... A89: 487 | B89: Lei 11.101/05 | C89: Art. 175 | D89: https://www.planalto.gov.br/ccivil_03/_ato2004-2006/2005/lei/l11101.htm | Z89: Apresentação de relação ou habilitação de créditos falsa em falência ou recuperação | AA89: Sim
A90: 547 | B90: Lei 1.579/52 | C90: Art. 4º, I | D90: https://www.planalto.gov.br/ccivil_03/leis/l1579.htm | E90: sim | Z90: Impedimento ou tentativa de impedimento de funcionamento de CPI | AA90: Sim
A91: 1320 | B91: ECA | C91: Art. 240, §1º, I | D91: https://www.planalto.gov.br/ccivil_03/leis/l8069compilado.htm | E91: sim | Z91: Agenciamento, recrutamento ou intermediação da participação de criança ou adolescente em cena de sexo explícito | AA91: Sim
A92: 919 | B92: DL 6.259/44 | C92: Art. 54 | D92: https://www.planalto.gov.br/ccivil_03/decreto-lei/1937-1946/del6259.htm | Z92: Falsificação, emenda ou adulteração de bilhete de loteria | AA92: Sim
A93: 394 | B93: Lei 9.613/98 | C93: Art. 1º, §5º | D93: https://www.planalto.gov.br/ccivil_03/leis/l9613.htm | Z93: Lavagem de dinheiro com diminuição de 1/3 a 2/3 (colaboração espontânea) | AA93: Sim
A94: 952 | B94: CE (Lei 4.737/65) | C94: Art. 354 | D94: https://www.planalto.gov.br/ccivil_03/leis/l4737compilado.htm | Z94: Obtenção de documento falso para fins eleitorais | AA94: Sim
A95: 1473 | B95: Lei 2.889/56 | C95: Art. 3º, §1º c/c art. 1º, b | D95: https://www.planalto.gov.br/ccivil_03/leis/l2889.htm | Z95: Incitação ao genocídio com crime consumado — lesão grave a membros do grupo | AA95: Sim
A96: 1469 | B96: Lei 2.889/56 | C96: Art. 3º c/c art. 1º, c | D96: https://www.planalto.gov.br/ccivil_03/leis/l2889.htm | Z96: Incitação ao genocídio — condições de existência destrutivas | AA96: Sim
A97: 829 | B97: LCP (DL 3.688/41) | C97: Art. 30 | D97: https://www.planalto.gov.br/ccivil_03/decreto-lei/del3688.htm | Z97: Perigo de desabamento | AA97: Sim
A98: 1326 | B98: Lei 7.716/89 | C98: Art. 20, §2º-B | D98: https://www.planalto.gov.br/ccivil_03/leis/l7716.htm | Z98: Obstrução ou violência contra manifestações ou práticas religiosas | AA98: Sim
A99: 904 | B99: DL 201/67 | C99: Art. 1º, III a XXIII | D99: https://www.planalto.gov.br/ccivil_03/decreto-lei/del0201.htm | Z99: Crime de responsabilidade de prefeito — demais condutas (itens III a XXIII): desvio de verba, contratação irregular, negativa de execução de lei, entre outras | AA99: Sim
A100: 1321 | B100: ECA | C100: Art. 240, §1º, II | D100: https://www.planalto.gov.br/ccivil_03/leis/l8069compilado.htm | Z100: Exibição ou transmissão em tempo real, pela internet ou meio digital, de cena de sexo explícito com criança ou adolescente | AA100: Sim
A101: 1530 | B101: Lei 6.538/78 | C101: Art. 40, §1º | D101: https://www.planalto.gov.br/ccivil_03/leis/l6538.htm | Z101: Sonegação ou destruição de correspondência | AA101: Sim

Sheet Revisor B
A1: id | B1: diploma | C1: dispositivo | D1: link do compilado | E1: dupla | F1: pena mínima (meses) | G1: ressalva | H1: pena máxima (meses) | I1: ressalva | J1: espécie de pena | K1: ressalva | L1: hediondo | M1: ressalva | N1: violência | O1: ressalva | P1: grave ameaça | Q1: ressalva | R1: elemento subjetivo | S1: ressalva | T1: admite tentativa | U1: ressalva | V1: ação penal | W1: ressalva | X1: tempo (min) | Y1: observações | Z1: nome publicado | AA1: vigente (publicado) | AB1: nome confere? | AC1: vigência confere?
A2: 165 | B2: CP | C2: Art. 211 | D2: https://www.planalto.gov.br/ccivil_03/decreto-lei/del2848compilado.htm | E2: sim | Z2: Destruição, subtração ou ocultação de cadáver | AA2: Sim
A3: 1335 | B3: CP | C3: Art. 254 (no caso de culpa) | D3: https://www.planalto.gov.br/ccivil_03/decreto-lei/del2848compilado.htm | E3: sim | Z3: Inundação — modalidade culposa | AA3: Sim
A4: 172 | B4: CP | C4: Art. 235 | D4: https://www.planalto.gov.br/ccivil_03/decreto-lei/del2848compilado.htm | E4: sim | Z4: Bigamia | AA4: Sim
A5: 994 | B5: CP | C5: Art. 162, caput | D5: https://www.planalto.gov.br/ccivil_03/decreto-lei/del2848compilado.htm | E5: sim | Z5: Alteração de marca ou sinal indicativo de propriedade de gado ou rebanho | AA5: Sim
A6: 70 | B6: CP | C6: Art. 148, §1º | D6: https://www.planalto.gov.br/ccivil_03/decreto-lei/del2848compilado.htm | E6: sim | Z6: Sequestro qualificado (fins libidinosos, menor de 18, maus-tratos, mais de 15 dias) | AA6: Sim
A7: 66 | B7: CP | C7: Art. 147 | D7: https://www.planalto.gov.br/ccivil_03/decreto-lei/del2848compilado.htm | E7: sim | Z7: Ameaça | AA7: Sim
A8: 706 | B8: CPM (DL 1.001/69) | C8: Art. 291, caput | D8: https://www.planalto.gov.br/ccivil_03/decreto-lei/del1001compilado.htm | E8: sim | Z8: Receita ilegal | AA8: Sim
A9: 1196 | B9: CPM (DL 1.001/69) | C9: Art. 326, caput | D9: https://www.planalto.gov.br/ccivil_03/decreto-lei/del1001compilado.htm | E9: sim | Z9: Violação de sigilo funcional | AA9: Sim
A10: 1108 | B10: CPM (DL 1.001/69) | C10: Art. 235, caput | D10: https://www.planalto.gov.br/ccivil_03/decreto-lei/del1001compilado.htm | E10: sim | Z10: Ato de libidinagem | AA10: Sim
A11: 1050 | B11: CPM (DL 1.001/69) | C11: Art. 172, caput | D11: https://www.planalto.gov.br/ccivil_03/decreto-lei/del1001compilado.htm | E11: sim | Z11: Uso indevido de uniforme, distintivo ou insígnia militar por qualquer pessoa | AA11: Sim
A12: 1437 | B12: CPM (DL 1.001/69) | C12: Art. 404 c/c art. 240, §5º | D12: https://www.planalto.gov.br/ccivil_03/decreto-lei/del1001compilado.htm | E12: sim | Z12: Furto qualificado — coisa pertencente à Fazenda Pública (tempo de guerra) | AA12: Sim
A13: 1298 | B13: Lei 1.521/51 | C13: Art. 4º, b | D13: https://www.planalto.gov.br/ccivil_03/leis/l1521.htm | E13: sim | Z13: Usura real | AA13: Sim
... A21: 1320 | B21: ECA | C21: Art. 240, §1º, I | D21: https://www.planalto.gov.br/ccivil_03/leis/l8069compilado.htm | E21: sim | Z21: Agenciamento, recrutamento ou intermediação da participação de criança ou adolescente em cena de sexo explícito | AA21: Sim

Sheet Apuração A
A1: id | B1: estrato | C1: pena_min | D1: pena_max | E1: tipo_pena | F1: hediondo | G1: violencia | H1: grave_ameaca | I1: elemento | J1: tentativa | K1: acao | L1: nome | M1: vigência | N1: divergências S1 | O1: saída do registro
A2: ='Revisor A'!A2 | B2: =IFERROR(INDEX(Gabarito!$M:$M,MATCH($A2,Gabarito!$A:$A,0)),"") | C2: =IF('Revisor A'!G2<>"",'Revisor A'!G2,IF('Revisor A'!F2="","não preenchido",IF(ABS(N('Revisor A'!F2)-N(INDEX(Gabarito!$B:$B,MATCH($A2,Gabarito!$A:$A,0))))<=1,"confere","diverge"))) | D2: =IF('Revisor A'!I2<>"",'Revisor A'!I2,IF('Revisor A'!H2="","não preenchido",IF(ABS(N('Revisor A'!H2)-N(INDEX(Gabarito!$C:$C,MATCH($A2,Gabarito!$A:$A,0))))<=1,"confere","diverge"))) | E2: =IF('Revisor A'!K2<>"",'Revisor A'!K2,IF('Revisor A'!J2="","não preenchido",IF(LOWER(TRIM('Revisor A'!J2))=LOWER(TRIM(INDEX(Gabarito!$D:$D,MATCH($A2,Gabarito!$A:$A,0)))),"confere","diverge"))) | F2: =IF('Revisor A'!M2<>"",'Revisor A'!M2,IF('Revisor A'!L2="","não preenchido",IF(LOWER(TRIM('Revisor A'!L2))=LOWER(TRIM(INDEX(Gabarito!$E:$E,MATCH($A2,Gabarito!$A:$A,0)))),"confere","diverge"))) | G2: =IF('Revisor A'!O2<>"",'Revisor A'!O2,IF('Revisor A'!N2="","não preenchido",IF(LOWER(TRIM('Revisor A'!N2))=LOWER(TRIM(INDEX(Gabarito!$F:$F,MATCH($A2,Gabarito!$A:$A,0)))),"confere","diverge"))) | H2: =IF('Revisor A'!Q2<>"",'Revisor A'!Q2,IF('Revisor A'!P2="","não preenchido",IF(LOWER(TRIM('Revisor A'!P2))=LOWER(TRIM(INDEX(Gabarito!$G:$G,MATCH($A2,Gabarito!$A:$A,0)))),"confere","diverge"))) | I2: =IF('Revisor A'!S2<>"",'Revisor A'!S2,IF('Revisor A'!R2="","não preenchido",IF(LOWER(TRIM('Revisor A'!R2))=LOWER(TRIM(INDEX(Gabarito!$H:$H,MATCH($A2,Gabarito!$A:$A,0)))),"confere","diverge"))) | J2: =IF('Revisor A'!U2<>"",'Revisor A'!U2,IF('Revisor A'!T2="","não preenchido",IF(LOWER(TRIM('Revisor A'!T2))=LOWER(TRIM(INDEX(Gabarito!$I:$I,MATCH($A2,Gabarito!$A:$A,0)))),"confere","diverge"))) | K2: =IF('Revisor A'!W2<>"",'Revisor A'!W2,IF('Revisor A'!V2="","não preenchido",IF(LOWER(TRIM('Revisor A'!V2))=LOWER(TRIM(INDEX(Gabarito!$J:$J,MATCH($A2,Gabarito!$A:$A,0)))),"confere","diverge"))) | L2: =IF('Revisor A'!AB2="","não preenchido",'Revisor A'!AB2) | M2: =IF('Revisor A'!AC2="","não preenchido",'Revisor A'!AC2) | N2: =COUNTIF(C2:K2,"diverge") | O2: =IF(COUNTIF(C2:K2,"não preenchido")=9,"não preenchido",IF(N2>0,"diverge","confere"))
A3: ='Revisor A'!A3 | B3: =IFERROR(INDEX(Gabarito!$M:$M,MATCH($A3,Gabarito!$A:$A,0)),"") | C3: =IF('Revisor A'!G3<>"",'Revisor A'!G3,IF('Revisor A'!F3="","não preenchido",IF(ABS(N('Revisor A'!F3)-N(INDEX(Gabarito!$B:$B,MATCH($A3,Gabarito!$A:$A,0))))<=1,"confere","diverge"))) | D3: =IF('Revisor A'!I3<>"",'Revisor A'!I3,IF('Revisor A'!H3="","não preenchido",IF(ABS(N('Revisor A'!H3)-N(INDEX(Gabarito!$C:$C,MATCH($A3,Gabarito!$A:$A,0))))<=1,"confere","diverge"))) | E3: =IF('Revisor A'!K3<>"",'Revisor A'!K3,IF('Revisor A'!J3="","não preenchido",IF(LOWER(TRIM('Revisor A'!J3))=LOWER(TRIM(INDEX(Gabarito!$D:$D,MATCH($A3,Gabarito!$A:$A,0)))),"confere","diverge"))) | F3: =IF('Revisor A'!M3<>"",'Revisor A'!M3,IF('Revisor A'!L3="","não preenchido",IF(LOWER(TRIM('Revisor A'!L3))=LOWER(TRIM(INDEX(Gabarito!$E:$E,MATCH($A3,Gabarito!$A:$A,0)))),"confere","diverge"))) | G3: =IF('Revisor A'!O3<>"",'Revisor A'!O3,IF('Revisor A'!N3="","não preenchido",IF(LOWER(TRIM('Revisor A'!N3))=LOWER(TRIM(INDEX(Gabarito!$F:$F,MATCH($A3,Gabarito!$A:$A,0)))),"confere","diverge"))) | H3: =IF('Revisor A'!Q3<>"",'Revisor A'!Q3,IF('Revisor A'!P3="","não preenchido",IF(LOWER(TRIM('Revisor A'!P3))=LOWER(TRIM(INDEX(Gabarito!$G:$G,MATCH($A3,Gabarito!$A:$A,0)))),"confere","diverge"))) | I3: =IF('Revisor A'!S3<>"",'Revisor A'!S3,IF('Revisor A'!R3="","não preenchido",IF(LOWER(TRIM('Revisor A'!R3))=LOWER(TRIM(INDEX(Gabarito!$H:$H,MATCH($A3,Gabarito!$A:$A,0)))),"confere","diverge"))) | J3: =IF('Revisor A'!U3<>"",'Revisor A'!U3,IF('Revisor A'!T3="","não preenchido",IF(LOWER(TRIM('Revisor A'!T3))=LOWER(TRIM(INDEX(Gabarito!$I:$I,MATCH($A3,Gabarito!$A:$A,0)))),"confere","diverge"))) | K3: =IF('Revisor A'!W3<>"",'Revisor A'!W3,IF('Revisor A'!V3="","não preenchido",IF(LOWER(TRIM('Revisor A'!V3))=LOWER(TRIM(INDEX(Gabarito!$J:$J,MATCH($A3,Gabarito!$A:$A,0)))),"confere","diverge"))) | L3: =IF('Revisor A'!AB3="","não preenchido",'Revisor A'!AB3) | M3: =IF('Revisor A'!AC3="","não preenchido",'Revisor A'!AC3) | N3: =COUNTIF(C3:K3,"diverge") | O3: =IF(COUNTIF(C3:K3,"não preenchido")=9,"não preenchido",IF(N3>0,"diverge","confere"))
A4: ='Revisor A'!A4 | B4: =IFERROR(INDEX(Gabarito!$M:$M,MATCH($A4,Gabarito!$A:$A,0)),"") | C4: =IF('Revisor A'!G4<>"",'Revisor A'!G4,IF('Revisor A'!F4="","não preenchido",IF(ABS(N('Revisor A'!F4)-N(INDEX(Gabarito!$B:$B,MATCH($A4,Gabarito!$A:$A,0))))<=1,"confere","diverge"))) | D4: =IF('Revisor A'!I4<>"",'Revisor A'!I4,IF('Revisor A'!H4="","não preenchido",IF(ABS(N('Revisor A'!H4)-N(INDEX(Gabarito!$C:$C,MATCH($A4,Gabarito!$A:$A,0))))<=1,"confere","diverge"))) | E4: =IF('Revisor A'!K4<>"",'Revisor A'!K4,IF('Revisor A'!J4="","não preenchido",IF(LOWER(TRIM('Revisor A'!J4))=LOWER(TRIM(INDEX(Gabarito!$D:$D,MATCH($A4,Gabarito!$A:$A,0)))),"confere","diverge"))) | F4: =IF('Revisor A'!M4<>"",'Revisor A'!M4,IF('Revisor A'!L4="","não preenchido",IF(LOWER(TRIM('Revisor A'!L4))=LOWER(TRIM(INDEX(Gabarito!$E:$E,MATCH($A4,Gabarito!$A:$A,0)))),"confere","diverge"))) | G4: =IF('Revisor A'!O4<>"",'Revisor A'!O4,IF('Revisor A'!N4="","não preenchido",IF(LOWER(TRIM('Revisor A'!N4))=LOWER(TRIM(INDEX(Gabarito!$F:$F,MATCH($A4,Gabarito!$A:$A,0)))),"confere","diverge"))) | H4: =IF('Revisor A'!Q4<>"",'Revisor A'!Q4,IF('Revisor A'!P4="","não preenchido",IF(LOWER(TRIM('Revisor A'!P4))=LOWER(TRIM(INDEX(Gabarito!$G:$G,MATCH($A4,Gabarito!$A:$A,0)))),"confere","diverge"))) | I4: =IF('Revisor A'!S4<>"",'Revisor A'!S4,IF('Revisor A'!R4="","não preenchido",IF(LOWER(TRIM('Revisor A'!R4))=LOWER(TRIM(INDEX(Gabarito!$H:$H,MATCH($A4,Gabarito!$A:$A,0)))),"confere","diverge"))) | J4: =IF('Revisor A'!U4<>"",'Revisor A'!U4,IF('Revisor A'!T4="","não preenchido",IF(LOWER(TRIM('Revisor A'!T4))=LOWER(TRIM(INDEX(Gabarito!$I:$I,MATCH($A4,Gabarito!$A:$A,0)))),"confere","diverge"))) | K4: =IF('Revisor A'!W4<>"",'Revisor A'!W4,IF('Revisor A'!V4="","não preenchido",IF(LOWER(TRIM('Revisor A'!V4))=LOWER(TRIM(INDEX(Gabarito!$J:$J,MATCH($A4,Gabarito!$A:$A,0)))),"confere","diverge"))) | L4: =IF('Revisor A'!AB4="","não preenchido",'Revisor A'!AB4) | M4: =IF('Revisor A'!AC4="","não preenchido",'Revisor A'!AC4) | N4: =COUNTIF(C4:K4,"diverge") | O4: =IF(COUNTIF(C4:K4,"não preenchido")=9,"não preenchido",IF(N4>0,"diverge","confere"))
A5: ='Revisor A'!A5 | B5: =IFERROR(INDEX(Gabarito!$M:$M,MATCH($A5,Gabarito!$A:$A,0)),"") | C5: =IF('Revisor A'!G5<>"",'Revisor A'!G5,IF('Revisor A'!F5="","não preenchido",IF(ABS(N('Revisor A'!F5)-N(INDEX(Gabarito!$B:$B,MATCH($A5,Gabarito!$A:$A,0))))<=1,"confere","diverge"))) | D5: =IF('Revisor A'!I5<>"",'Revisor A'!I5,IF('Revisor A'!H5="","não preenchido",IF(ABS(N('Revisor A'!H5)-N(INDEX(Gabarito!$C:$C,MATCH($A5,Gabarito!$A:$A,0))))<=1,"confere","diverge"))) | E5: =IF('Revisor A'!K5<>"",'Revisor A'!K5,IF('Revisor A'!J5="","não preenchido",IF(LOWER(TRIM('Revisor A'!J5))=LOWER(TRIM(INDEX(Gabarito!$D:$D,MATCH($A5,Gabarito!$A:$A,0)))),"confere","diverge"))) | F5: =IF('Revisor A'!M5<>"",'Revisor A'!M5,IF('Revisor A'!L5="","não preenchido",IF(LOWER(TRIM('Revisor A'!L5))=LOWER(TRIM(INDEX(Gabarito!$E:$E,MATCH($A5,Gabarito!$A:$A,0)))),"confere","diverge"))) | G5: =IF('Revisor A'!O5<>"",'Revisor A'!O5,IF('Revisor A'!N5="","não preenchido",IF(LOWER(TRIM('Revisor A'!N5))=LOWER(TRIM(INDEX(Gabarito!$F:$F,MATCH($A5,Gabarito!$A:$A,0)))),"confere","diverge"))) | H5: =IF('Revisor A'!Q5<>"",'Revisor A'!Q5,IF('Revisor A'!P5="","não preenchido",IF(LOWER(TRIM('Revisor A'!P5))=LOWER(TRIM(INDEX(Gabarito!$G:$G,MATCH($A5,Gabarito!$A:$A,0)))),"confere","diverge"))) | I5: =IF('Revisor A'!S5<>"",'Revisor A'!S5,IF('Revisor A'!R5="","não preenchido",IF(LOWER(TRIM('Revisor A'!R5))=LOWER(TRIM(INDEX(Gabarito!$H:$H,MATCH($A5,Gabarito!$A:$A,0)))),"confere","diverge"))) | J5: =IF('Revisor A'!U5<>"",'Revisor A'!U5,IF('Revisor A'!T5="","não preenchido",IF(LOWER(TRIM('Revisor A'!T5))=LOWER(TRIM(INDEX(Gabarito!$I:$I,MATCH($A5,Gabarito!$A:$A,0)))),"confere","diverge"))) | K5: =IF('Revisor A'!W5<>"",'Revisor A'!W5,IF('Revisor A'!V5="","não preenchido",IF(LOWER(TRIM('Revisor A'!V5))=LOWER(TRIM(INDEX(Gabarito!$J:$J,MATCH($A5,Gabarito!$A:$A,0)))),"confere","diverge"))) | L5: =IF('Revisor A'!AB5="","não preenchido",'Revisor A'!AB5) | M5: =IF('Revisor A'!AC5="","não preenchido",'Revisor A'!AC5) | N5: =COUNTIF(C5:K5,"diverge") | O5: =IF(COUNTIF(C5:K5,"não preenchido")=9,"não preenchido",IF(N5>0,"diverge","confere"))
A6: ='Revisor A'!A6 | B6: =IFERROR(INDEX(Gabarito!$M:$M,MATCH($A6,Gabarito!$A:$A,0)),"") | C6: =IF('Revisor A'!G6<>"",'Revisor A'!G6,IF('Revisor A'!F6="","não preenchido",IF(ABS(N('Revisor A'!F6)-N(INDEX(Gabarito!$B:$B,MATCH($A6,Gabarito!$A:$A,0))))<=1,"confere","diverge"))) | D6: =IF('Revisor A'!I6<>"",'Revisor A'!I6,IF('Revisor A'!H6="","não preenchido",IF(ABS(N('Revisor A'!H6)-N(INDEX(Gabarito!$C:$C,MATCH($A6,Gabarito!$A:$A,0))))<=1,"confere","diverge"))) | E6: =IF('Revisor A'!K6<>"",'Revisor A'!K6,IF('Revisor A'!J6="","não preenchido",IF(LOWER(TRIM('Revisor A'!J6))=LOWER(TRIM(INDEX(Gabarito!$D:$D,MATCH($A6,Gabarito!$A:$A,0)))),"confere","diverge"))) | F6: =IF('Revisor A'!M6<>"",'Revisor A'!M6,IF('Revisor A'!L6="","não preenchido",IF(LOWER(TRIM('Revisor A'!L6))=LOWER(TRIM(INDEX(Gabarito!$E:$E,MATCH($A6,Gabarito!$A:$A,0)))),"confere","diverge"))) | G6: =IF('Revisor A'!O6<>"",'Revisor A'!O6,IF('Revisor A'!N6="","não preenchido",IF(LOWER(TRIM('Revisor A'!N6))=LOWER(TRIM(INDEX(Gabarito!$F:$F,MATCH($A6,Gabarito!$A:$A,0)))),"confere","diverge"))) | H6: =IF('Revisor A'!Q6<>"",'Revisor A'!Q6,IF('Revisor A'!P6="","não preenchido",IF(LOWER(TRIM('Revisor A'!P6))=LOWER(TRIM(INDEX(Gabarito!$G:$G,MATCH($A6,Gabarito!$A:$A,0)))),"confere","diverge"))) | I6: =IF('Revisor A'!S6<>"",'Revisor A'!S6,IF('Revisor A'!R6="","não preenchido",IF(LOWER(TRIM('Revisor A'!R6))=LOWER(TRIM(INDEX(Gabarito!$H:$H,MATCH($A6,Gabarito!$A:$A,0)))),"confere","diverge"))) | J6: =IF('Revisor A'!U6<>"",'Revisor A'!U6,IF('Revisor A'!T6="","não preenchido",IF(LOWER(TRIM('Revisor A'!T6))=LOWER(TRIM(INDEX(Gabarito!$I:$I,MATCH($A6,Gabarito!$A:$A,0)))),"confere","diverge"))) | K6: =IF('Revisor A'!W6<>"",'Revisor A'!W6,IF('Revisor A'!V6="","não preenchido",IF(LOWER(TRIM('Revisor A'!V6))=LOWER(TRIM(INDEX(Gabarito!$J:$J,MATCH($A6,Gabarito!$A:$A,0)))),"confere","diverge"))) | L6: =IF('Revisor A'!AB6="","não preenchido",'Revisor A'!AB6) | M6: =IF('Revisor A'!AC6="","não preenchido",'Revisor A'!AC6) | N6: =COUNTIF(C6:K6,"diverge") | O6: =IF(COUNTIF(C6:K6,"não preenchido")=9,"não preenchido",IF(N6>0,"diverge","confere"))
A7: ='Revisor A'!A7 | B7: =IFERROR(INDEX(Gabarito!$M:$M,MATCH($A7,Gabarito!$A:$A,0)),"") | C7: =IF('Revisor A'!G7<>"",'Revisor A'!G7,IF('Revisor A'!F7="","não preenchido",IF(ABS(N('Revisor A'!F7)-N(INDEX(Gabarito!$B:$B,MATCH($A7,Gabarito!$A:$A,0))))<=1,"confere","diverge"))) | D7: =IF('Revisor A'!I7<>"",'Revisor A'!I7,IF('Revisor A'!H7="","não preenchido",IF(ABS(N('Revisor A'!H7)-N(INDEX(Gabarito!$C:$C,MATCH($A7,Gabarito!$A:$A,0))))<=1,"confere","diverge"))) | E7: =IF('Revisor A'!K7<>"",'Revisor A'!K7,IF('Revisor A'!J7="","não preenchido",IF(LOWER(TRIM('Revisor A'!J7))=LOWER(TRIM(INDEX(Gabarito!$D:$D,MATCH($A7,Gabarito!$A:$A,0)))),"confere","diverge"))) | F7: =IF('Revisor A'!M7<>"",'Revisor A'!M7,IF('Revisor A'!L7="","não preenchido",IF(LOWER(TRIM('Revisor A'!L7))=LOWER(TRIM(INDEX(Gabarito!$E:$E,MATCH($A7,Gabarito!$A:$A,0)))),"confere","diverge"))) | G7: =IF('Revisor A'!O7<>"",'Revisor A'!O7,IF('Revisor A'!N7="","não preenchido",IF(LOWER(TRIM('Revisor A'!N7))=LOWER(TRIM(INDEX(Gabarito!$F:$F,MATCH($A7,Gabarito!$A:$A,0)))),"confere","diverge"))) | H7: =IF('Revisor A'!Q7<>"",'Revisor A'!Q7,IF('Revisor A'!P7="","não preenchido",IF(LOWER(TRIM('Revisor A'!P7))=LOWER(TRIM(INDEX(Gabarito!$G:$G,MATCH($A7,Gabarito!$A:$A,0)))),"confere","diverge"))) | I7: =IF('Revisor A'!S7<>"",'Revisor A'!S7,IF('Revisor A'!R7="","não preenchido",IF(LOWER(TRIM('Revisor A'!R7))=LOWER(TRIM(INDEX(Gabarito!$H:$H,MATCH($A7,Gabarito!$A:$A,0)))),"confere","diverge"))) | J7: =IF('Revisor A'!U7<>"",'Revisor A'!U7,IF('Revisor A'!T7="","não preenchido",IF(LOWER(TRIM('Revisor A'!T7))=LOWER(TRIM(INDEX(Gabarito!$I:$I,MATCH($A7,Gabarito!$A:$A,0)))),"confere","diverge"))) | K7: =IF('Revisor A'!W7<>"",'Revisor A'!W7,IF('Revisor A'!V7="","não preenchido",IF(LOWER(TRIM('Revisor A'!V7))=LOWER(TRIM(INDEX(Gabarito!$J:$J,MATCH($A7,Gabarito!$A:$A,0)))),"confere","diverge"))) | L7: =IF('Revisor A'!AB7="","não preenchido",'Revisor A'!AB7) | M7: =IF('Revisor A'!AC7="","não preenchido",'Revisor A'!AC7) | N7: =COUNTIF(C7:K7,"diverge") | O7: =IF(COUNTIF(C7:K7,"não preenchido")=9,"não preenchido",IF(N7>0,"diverge","confere"))
A8: ='Revisor A'!A8 | B8: =IFERROR(INDEX(Gabarito!$M:$M,MATCH($A8,Gabarito!$A:$A,0)),"") | C8: =IF('Revisor A'!G8<>"",'Revisor A'!G8,IF('Revisor A'!F8="","não preenchido",IF(ABS(N('Revisor A'!F8)-N(INDEX(Gabarito!$B:$B,MATCH($A8,Gabarito!$A:$A,0))))<=1,"confere","diverge"))) | D8: =IF('Revisor A'!I8<>"",'Revisor A'!I8,IF('Revisor A'!H8="","não preenchido",IF(ABS(N('Revisor A'!H8)-N(INDEX(Gabarito!$C:$C,MATCH($A8,Gabarito!$A:$A,0))))<=1,"confere","diverge"))) | E8: =IF('Revisor A'!K8<>"",'Revisor A'!K8,IF('Revisor A'!J8="","não preenchido",IF(LOWER(TRIM('Revisor A'!J8))=LOWER(TRIM(INDEX(Gabarito!$D:$D,MATCH($A8,Gabarito!$A:$A,0)))),"confere","diverge"))) | F8: =IF('Revisor A'!M8<>"",'Revisor A'!M8,IF('Revisor A'!L8="","não preenchido",IF(LOWER(TRIM('Revisor A'!L8))=LOWER(TRIM(INDEX(Gabarito!$E:$E,MATCH($A8,Gabarito!$A:$A,0)))),"confere","diverge"))) | G8: =IF('Revisor A'!O8<>"",'Revisor A'!O8,IF('Revisor A'!N8="","não preenchido",IF(LOWER(TRIM('Revisor A'!N8))=LOWER(TRIM(INDEX(Gabarito!$F:$F,MATCH($A8,Gabarito!$A:$A,0)))),"confere","diverge"))) | H8: =IF('Revisor A'!Q8<>"",'Revisor A'!Q8,IF('Revisor A'!P8="","não preenchido",IF(LOWER(TRIM('Revisor A'!P8))=LOWER(TRIM(INDEX(Gabarito!$G:$G,MATCH($A8,Gabarito!$A:$A,0)))),"confere","diverge"))) | I8: =IF('Revisor A'!S8<>"",'Revisor A'!S8,IF('Revisor A'!R8="","não preenchido",IF(LOWER(TRIM('Revisor A'!R8))=LOWER(TRIM(INDEX(Gabarito!$H:$H,MATCH($A8,Gabarito!$A:$A,0)))),"confere","diverge"))) | J8: =IF('Revisor A'!U8<>"",'Revisor A'!U8,IF('Revisor A'!T8="","não preenchido",IF(LOWER(TRIM('Revisor A'!T8))=LOWER(TRIM(INDEX(Gabarito!$I:$I,MATCH($A8,Gabarito!$A:$A,0)))),"confere","diverge"))) | K8: =IF('Revisor A'!W8<>"",'Revisor A'!W8,IF('Revisor A'!V8="","não preenchido",IF(LOWER(TRIM('Revisor A'!V8))=LOWER(TRIM(INDEX(Gabarito!$J:$J,MATCH($A8,Gabarito!$A:$A,0)))),"confere","diverge"))) | L8: =IF('Revisor A'!AB8="","não preenchido",'Revisor A'!AB8) | M8: =IF('Revisor A'!AC8="","não preenchido",'Revisor A'!AC8) | N8: =COUNTIF(C8:K8,"diverge") | O8: =IF(COUNTIF(C8:K8,"não preenchido")=9,"não preenchido",IF(N8>0,"diverge","confere"))
A9: ='Revisor A'!A9 | B9: =IFERROR(INDEX(Gabarito!$M:$M,MATCH($A9,Gabarito!$A:$A,0)),"") | C9: =IF('Revisor A'!G9<>"",'Revisor A'!G9,IF('Revisor A'!F9="","não preenchido",IF(ABS(N('Revisor A'!F9)-N(INDEX(Gabarito!$B:$B,MATCH($A9,Gabarito!$A:$A,0))))<=1,"confere","diverge"))) | D9: =IF('Revisor A'!I9<>"",'Revisor A'!I9,IF('Revisor A'!H9="","não preenchido",IF(ABS(N('Revisor A'!H9)-N(INDEX(Gabarito!$C:$C,MATCH($A9,Gabarito!$A:$A,0))))<=1,"confere","diverge"))) | E9: =IF('Revisor A'!K9<>"",'Revisor A'!K9,IF('Revisor A'!J9="","não preenchido",IF(LOWER(TRIM('Revisor A'!J9))=LOWER(TRIM(INDEX(Gabarito!$D:$D,MATCH($A9,Gabarito!$A:$A,0)))),"confere","diverge"))) | F9: =IF('Revisor A'!M9<>"",'Revisor A'!M9,IF('Revisor A'!L9="","não preenchido",IF(LOWER(TRIM('Revisor A'!L9))=LOWER(TRIM(INDEX(Gabarito!$E:$E,MATCH($A9,Gabarito!$A:$A,0)))),"confere","diverge"))) | G9: =IF('Revisor A'!O9<>"",'Revisor A'!O9,IF('Revisor A'!N9="","não preenchido",IF(LOWER(TRIM('Revisor A'!N9))=LOWER(TRIM(INDEX(Gabarito!$F:$F,MATCH($A9,Gabarito!$A:$A,0)))),"confere","diverge"))) | H9: =IF('Revisor A'!Q9<>"",'Revisor A'!Q9,IF('Revisor A'!P9="","não preenchido",IF(LOWER(TRIM('Revisor A'!P9))=LOWER(TRIM(INDEX(Gabarito!$G:$G,MATCH($A9,Gabarito!$A:$A,0)))),"confere","diverge"))) | I9: =IF('Revisor A'!S9<>"",'Revisor A'!S9,IF('Revisor A'!R9="","não preenchido",IF(LOWER(TRIM('Revisor A'!R9))=LOWER(TRIM(INDEX(Gabarito!$H:$H,MATCH($A9,Gabarito!$A:$A,0)))),"confere","diverge"))) | J9: =IF('Revisor A'!U9<>"",'Revisor A'!U9,IF('Revisor A'!T9="","não preenchido",IF(LOWER(TRIM('Revisor A'!T9))=LOWER(TRIM(INDEX(Gabarito!$I:$I,MATCH($A9,Gabarito!$A:$A,0)))),"confere","diverge"))) | K9: =IF('Revisor A'!W9<>"",'Revisor A'!W9,IF('Revisor A'!V9="","não preenchido",IF(LOWER(TRIM('Revisor A'!V9))=LOWER(TRIM(INDEX(Gabarito!$J:$J,MATCH($A9,Gabarito!$A:$A,0)))),"confere","diverge"))) | L9: =IF('Revisor A'!AB9="","não preenchido",'Revisor A'!AB9) | M9: =IF('Revisor A'!AC9="","não preenchido",'Revisor A'!AC9) | N9: =COUNTIF(C9:K9,"diverge") | O9: =IF(COUNTIF(C9:K9,"não preenchido")=9,"não preenchido",IF(N9>0,"diverge","confere"))
A10: ='Revisor A'!A10 | B10: =IFERROR(INDEX(Gabarito!$M:$M,MATCH($A10,Gabarito!$A:$A,0)),"") | C10: =IF('Revisor A'!G10<>"",'Revisor A'!G10,IF('Revisor A'!F10="","não preenchido",IF(ABS(N('Revisor A'!F10)-N(INDEX(Gabarito!$B:$B,MATCH($A10,Gabarito!$A:$A,0))))<=1,"confere","diverge"))) | D10: =IF('Revisor A'!I10<>"",'Revisor A'!I10,IF('Revisor A'!H10="","não preenchido",IF(ABS(N('Revisor A'!H10)-N(INDEX(Gabarito!$C:$C,MATCH($A10,Gabarito!$A:$A,0))))<=1,"confere","diverge"))) | E10: =IF('Revisor A'!K10<>"",'Revisor A'!K10,IF('Revisor A'!J10="","não preenchido",IF(LOWER(TRIM('Revisor A'!J10))=LOWER(TRIM(INDEX(Gabarito!$D:$D,MATCH($A10,Gabarito!$A:$A,0)))),"confere","diverge"))) | F10: =IF('Revisor A'!M10<>"",'Revisor A'!M10,IF('Revisor A'!L10="","não preenchido",IF(LOWER(TRIM('Revisor A'!L10))=LOWER(TRIM(INDEX(Gabarito!$E:$E,MATCH($A10,Gabarito!$A:$A,0)))),"confere","diverge"))) | G10: =IF('Revisor A'!O10<>"",'Revisor A'!O10,IF('Revisor A'!N10="","não preenchido",IF(LOWER(TRIM('Revisor A'!N10))=LOWER(TRIM(INDEX(Gabarito!$F:$F,MATCH($A10,Gabarito!$A:$A,0)))),"confere","diverge"))) | H10: =IF('Revisor A'!Q10<>"",'Revisor A'!Q10,IF('Revisor A'!P10="","não preenchido",IF(LOWER(TRIM('Revisor A'!P10))=LOWER(TRIM(INDEX(Gabarito!$G:$G,MATCH($A10,Gabarito!$A:$A,0)))),"confere","diverge"))) | I10: =IF('Revisor A'!S10<>"",'Revisor A'!S10,IF('Revisor A'!R10="","não preenchido",IF(LOWER(TRIM('Revisor A'!R10))=LOWER(TRIM(INDEX(Gabarito!$H:$H,MATCH($A10,Gabarito!$A:$A,0)))),"confere","diverge"))) | J10: =IF('Revisor A'!U10<>"",'Revisor A'!U10,IF('Revisor A'!T10="","não preenchido",IF(LOWER(TRIM('Revisor A'!T10))=LOWER(TRIM(INDEX(Gabarito!$I:$I,MATCH($A10,Gabarito!$A:$A,0)))),"confere","diverge"))) | K10: =IF('Revisor A'!W10<>"",'Revisor A'!W10,IF('Revisor A'!V10="","não preenchido",IF(LOWER(TRIM('Revisor A'!V10))=LOWER(TRIM(INDEX(Gabarito!$J:$J,MATCH($A10,Gabarito!$A:$A,0)))),"confere","diverge"))) | L10: =IF('Revisor A'!AB10="","não preenchido",'Revisor A'!AB10) | M10: =IF('Revisor A'!AC10="","não preenchido",'Revisor A'!AC10) | N10: =COUNTIF(C10:K10,"diverge") | O10: =IF(COUNTIF(C10:K10,"não preenchido")=9,"não preenchido",IF(N10>0,"diverge","confere"))
A11: ='Revisor A'!A11 | B11: =IFERROR(INDEX(Gabarito!$M:$M,MATCH($A11,Gabarito!$A:$A,0)),"") | C11: =IF('Revisor A'!G11<>"",'Revisor A'!G11,IF('Revisor A'!F11="","não preenchido",IF(ABS(N('Revisor A'!F11)-N(INDEX(Gabarito!$B:$B,MATCH($A11,Gabarito!$A:$A,0))))<=1,"confere","diverge"))) | D11: =IF('Revisor A'!I11<>"",'Revisor A'!I11,IF('Revisor A'!H11="","não preenchido",IF(ABS(N('Revisor A'!H11)-N(INDEX(Gabarito!$C:$C,MATCH($A11,Gabarito!$A:$A,0))))<=1,"confere","diverge"))) | E11: =IF('Revisor A'!K11<>"",'Revisor A'!K11,IF('Revisor A'!J11="","não preenchido",IF(LOWER(TRIM('Revisor A'!J11))=LOWER(TRIM(INDEX(Gabarito!$D:$D,MATCH($A11,Gabarito!$A:$A,0)))),"confere","diverge"))) | F11: =IF('Revisor A'!M11<>"",'Revisor A'!M11,IF('Revisor A'!L11="","não preenchido",IF(LOWER(TRIM('Revisor A'!L11))=LOWER(TRIM(INDEX(Gabarito!$E:$E,MATCH($A11,Gabarito!$A:$A,0)))),"confere","diverge"))) | G11: =IF('Revisor A'!O11<>"",'Revisor A'!O11,IF('Revisor A'!N11="","não preenchido",IF(LOWER(TRIM('Revisor A'!N11))=LOWER(TRIM(INDEX(Gabarito!$F:$F,MATCH($A11,Gabarito!$A:$A,0)))),"confere","diverge"))) | H11: =IF('Revisor A'!Q11<>"",'Revisor A'!Q11,IF('Revisor A'!P11="","não preenchido",IF(LOWER(TRIM('Revisor A'!P11))=LOWER(TRIM(INDEX(Gabarito!$G:$G,MATCH($A11,Gabarito!$A:$A,0)))),"confere","diverge"))) | I11: =IF('Revisor A'!S11<>"",'Revisor A'!S11,IF('Revisor A'!R11="","não preenchido",IF(LOWER(TRIM('Revisor A'!R11))=LOWER(TRIM(INDEX(Gabarito!$H:$H,MATCH($A11,Gabarito!$A:$A,0)))),"confere","diverge"))) | J11: =IF('Revisor A'!U11<>"",'Revisor A'!U11,IF('Revisor A'!T11="","não preenchido",IF(LOWER(TRIM('Revisor A'!T11))=LOWER(TRIM(INDEX(Gabarito!$I:$I,MATCH($A11,Gabarito!$A:$A,0)))),"confere","diverge"))) | K11: =IF('Revisor A'!W11<>"",'Revisor A'!W11,IF('Revisor A'!V11="","não preenchido",IF(LOWER(TRIM('Revisor A'!V11))=LOWER(TRIM(INDEX(Gabarito!$J:$J,MATCH($A11,Gabarito!$A:$A,0)))),"confere","diverge"))) | L11: =IF('Revisor A'!AB11="","não preenchido",'Revisor A'!AB11) | M11: =IF('Revisor A'!AC11="","não preenchido",'Revisor A'!AC11) | N11: =COUNTIF(C11:K11,"diverge") | O11: =IF(COUNTIF(C11:K11,"não preenchido")=9,"não preenchido",IF(N11>0,"diverge","confere"))
A12: ='Revisor A'!A12 | B12: =IFERROR(INDEX(Gabarito!$M:$M,MATCH($A12,Gabarito!$A:$A,0)),"") | C12: =IF('Revisor A'!G12<>"",'Revisor A'!G12,IF('Revisor A'!F12="","não preenchido",IF(ABS(N('Revisor A'!F12)-N(INDEX(Gabarito!$B:$B,MATCH($A12,Gabarito!$A:$A,0))))<=1,"confere","diverge"))) | D12: =IF('Revisor A'!I12<>"",'Revisor A'!I12,IF('Revisor A'!H12="","não preenchido",IF(ABS(N('Revisor A'!H12)-N(INDEX(Gabarito!$C:$C,MATCH($A12,Gabarito!$A:$A,0))))<=1,"confere","diverge"))) | E12: =IF('Revisor A'!K12<>"",'Revisor A'!K12,IF('Revisor A'!J12="","não preenchido",IF(LOWER(TRIM('Revisor A'!J12))=LOWER(TRIM(INDEX(Gabarito!$D:$D,MATCH($A12,Gabarito!$A:$A,0)))),"confere","diverge"))) | F12: =IF('Revisor A'!M12<>"",'Revisor A'!M12,IF('Revisor A'!L12="","não preenchido",IF(LOWER(TRIM('Revisor A'!L12))=LOWER(TRIM(INDEX(Gabarito!$E:$E,MATCH($A12,Gabarito!$A:$A,0)))),"confere","diverge"))) | G12: =IF('Revisor A'!O12<>"",'Revisor A'!O12,IF('Revisor A'!N12="","não preenchido",IF(LOWER(TRIM('Revisor A'!N12))=LOWER(TRIM(INDEX(Gabarito!$F:$F,MATCH($A12,Gabarito!$A:$A,0)))),"confere","diverge"))) | H12: =IF('Revisor A'!Q12<>"",'Revisor A'!Q12,IF('Revisor A'!P12="","não preenchido",IF(LOWER(TRIM('Revisor A'!P12))=LOWER(TRIM(INDEX(Gabarito!$G:$G,MATCH($A12,Gabarito!$A:$A,0)))),"confere","diverge"))) | I12: =IF('Revisor A'!S12<>"",'Revisor A'!S12,IF('Revisor A'!R12="","não preenchido",IF(LOWER(TRIM('Revisor A'!R12))=LOWER(TRIM(INDEX(Gabarito!$H:$H,MATCH($A12,Gabarito!$A:$A,0)))),"confere","diverge"))) | J12: =IF('Revisor A'!U12<>"",'Revisor A'!U12,IF('Revisor A'!T12="","não preenchido",IF(LOWER(TRIM('Revisor A'!T12))=LOWER(TRIM(INDEX(Gabarito!$I:$I,MATCH($A12,Gabarito!$A:$A,0)))),"confere","diverge"))) | K12: =IF('Revisor A'!W12<>"",'Revisor A'!W12,IF('Revisor A'!V12="","não preenchido",IF(LOWER(TRIM('Revisor A'!V12))=LOWER(TRIM(INDEX(Gabarito!$J:$J,MATCH($A12,Gabarito!$A:$A,0)))),"confere","diverge"))) | L12: =IF('Revisor A'!AB12="","não preenchido",'Revisor A'!AB12) | M12: =IF('Revisor A'!AC12="","não preenchido",'Revisor A'!AC12) | N12: =COUNTIF(C12:K12,"diverge") | O12: =IF(COUNTIF(C12:K12,"não preenchido")=9,"não preenchido",IF(N12>0,"diverge","confere"))
A13: ='Revisor A'!A13 | B13: =IFERROR(INDEX(Gabarito!$M:$M,MATCH($A13,Gabarito!$A:$A,0)),"") | C13: =IF('Revisor A'!G13<>"",'Revisor A'!G13,IF('Revisor A'!F13="","não preenchido",IF(ABS(N('Revisor A'!F13)-N(INDEX(Gabarito!$B:$B,MATCH($A13,Gabarito!$A:$A,0))))<=1,"confere","diverge"))) | D13: =IF('Revisor A'!I13<>"",'Revisor A'!I13,IF('Revisor A'!H13="","não preenchido",IF(ABS(N('Revisor A'!H13)-N(INDEX(Gabarito!$C:$C,MATCH($A13,Gabarito!$A:$A,0))))<=1,"confere","diverge"))) | E13: =IF('Revisor A'!K13<>"",'Revisor A'!K13,IF('Revisor A'!J13="","não preenchido",IF(LOWER(TRIM('Revisor A'!J13))=LOWER(TRIM(INDEX(Gabarito!$D:$D,MATCH($A13,Gabarito!$A:$A,0)))),"confere","diverge"))) | F13: =IF('Revisor A'!M13<>"",'Revisor A'!M13,IF('Revisor A'!L13="","não preenchido",IF(LOWER(TRIM('Revisor A'!L13))=LOWER(TRIM(INDEX(Gabarito!$E:$E,MATCH($A13,Gabarito!$A:$A,0)))),"confere","diverge"))) | G13: =IF('Revisor A'!O13<>"",'Revisor A'!O13,IF('Revisor A'!N13="","não preenchido",IF(LOWER(TRIM('Revisor A'!N13))=LOWER(TRIM(INDEX(Gabarito!$F:$F,MATCH($A13,Gabarito!$A:$A,0)))),"confere","diverge"))) | H13: =IF('Revisor A'!Q13<>"",'Revisor A'!Q13,IF('Revisor A'!P13="","não preenchido",IF(LOWER(TRIM('Revisor A'!P13))=LOWER(TRIM(INDEX(Gabarito!$G:$G,MATCH($A13,Gabarito!$A:$A,0)))),"confere","diverge"))) | I13: =IF('Revisor A'!S13<>"",'Revisor A'!S13,IF('Revisor A'!R13="","não preenchido",IF(LOWER(TRIM('Revisor A'!R13))=LOWER(TRIM(INDEX(Gabarito!$H:$H,MATCH($A13,Gabarito!$A:$A,0)))),"confere","diverge"))) | J13: =IF('Revisor A'!U13<>"",'Revisor A'!U13,IF('Revisor A'!T13="","não preenchido",IF(LOWER(TRIM('Revisor A'!T13))=LOWER(TRIM(INDEX(Gabarito!$I:$I,MATCH($A13,Gabarito!$A:$A,0)))),"confere","diverge"))) | K13: =IF('Revisor A'!W13<>"",'Revisor A'!W13,IF('Revisor A'!V13="","não preenchido",IF(LOWER(TRIM('Revisor A'!V13))=LOWER(TRIM(INDEX(Gabarito!$J:$J,MATCH($A13,Gabarito!$A:$A,0)))),"confere","diverge"))) | L13: =IF('Revisor A'!AB13="","não preenchido",'Revisor A'!AB13) | M13: =IF('Revisor A'!AC13="","não preenchido",'Revisor A'!AC13) | N13: =COUNTIF(C13:K13,"diverge") | O13: =IF(COUNTIF(C13:K13,"não preenchido")=9,"não preenchido",IF(N13>0,"diverge","confere"))
... A101: ='Revisor A'!A101 | B101: =IFERROR(INDEX(Gabarito!$M:$M,MATCH($A101,Gabarito!$A:$A,0)),"") | C101: =IF('Revisor A'!G101<>"",'Revisor A'!G101,IF('Revisor A'!F101="","não preenchido",IF(ABS(N('Revisor A'!F101)-N(INDEX(Gabarito!$B:$B,MATCH($A101,Gabarito!$A:$A,0))))<=1,"confere","diverge"))) | D101: =IF('Revisor A'!I101<>"",'Revisor A'!I101,IF('Revisor A'!H101="","não preenchido",IF(ABS(N('Revisor A'!H101)-N(INDEX(Gabarito!$C:$C,MATCH($A101,Gabarito!$A:$A,0))))<=1,"confere","diverge"))) | E101: =IF('Revisor A'!K101<>"",'Revisor A'!K101,IF('Revisor A'!J101="","não preenchido",IF(LOWER(TRIM('Revisor A'!J101))=LOWER(TRIM(INDEX(Gabarito!$D:$D,MATCH($A101,Gabarito!$A:$A,0)))),"confere","diverge"))) | F101: =IF('Revisor A'!M101<>"",'Revisor A'!M101,IF('Revisor A'!L101="","não preenchido",IF(LOWER(TRIM('Revisor A'!L101))=LOWER(TRIM(INDEX(Gabarito!$E:$E,MATCH($A101,Gabarito!$A:$A,0)))),"confere","diverge"))) | G101: =IF('Revisor A'!O101<>"",'Revisor A'!O101,IF('Revisor A'!N101="","não preenchido",IF(LOWER(TRIM('Revisor A'!N101))=LOWER(TRIM(INDEX(Gabarito!$F:$F,MATCH($A101,Gabarito!$A:$A,0)))),"confere","diverge"))) | H101: =IF('Revisor A'!Q101<>"",'Revisor A'!Q101,IF('Revisor A'!P101="","não preenchido",IF(LOWER(TRIM('Revisor A'!P101))=LOWER(TRIM(INDEX(Gabarito!$G:$G,MATCH($A101,Gabarito!$A:$A,0)))),"confere","diverge"))) | I101: =IF('Revisor A'!S101<>"",'Revisor A'!S101,IF('Revisor A'!R101="","não preenchido",IF(LOWER(TRIM('Revisor A'!R101))=LOWER(TRIM(INDEX(Gabarito!$H:$H,MATCH($A101,Gabarito!$A:$A,0)))),"confere","diverge"))) | J101: =IF('Revisor A'!U101<>"",'Revisor A'!U101,IF('Revisor A'!T101="","não preenchido",IF(LOWER(TRIM('Revisor A'!T101))=LOWER(TRIM(INDEX(Gabarito!$I:$I,MATCH($A101,Gabarito!$A:$A,0)))),"confere","diverge"))) | K101: =IF('Revisor A'!W101<>"",'Revisor A'!W101,IF('Revisor A'!V101="","não preenchido",IF(LOWER(TRIM('Revisor A'!V101))=LOWER(TRIM(INDEX(Gabarito!$J:$J,MATCH($A101,Gabarito!$A:$A,0)))),"confere","diverge"))) | L101: =IF('Revisor A'!AB101="","não preenchido",'Revisor A'!AB101) | M101: =IF('Revisor A'!AC101="","não preenchido",'Revisor A'!AC101) | N101: =COUNTIF(C101:K101,"diverge") | O101: =IF(COUNTIF(C101:K101,"não preenchido")=9,"não preenchido",IF(N101>0,"diverge","confere"))

Sheet Apuração B
A1: id | B1: estrato | C1: pena_min | D1: pena_max | E1: tipo_pena | F1: hediondo | G1: violencia | H1: grave_ameaca | I1: elemento | J1: tentativa | K1: acao | L1: nome | M1: vigência | N1: divergências S1 | O1: saída do registro | P1: A: pena_min | Q1: A: pena_max | R1: A: tipo_pena | S1: A: hediondo | T1: A: violencia | U1: A: grave_ameaca | V1: A: elemento | W1: A: tentativa | X1: A: acao
A2: ='Revisor B'!A2 | B2: =IFERROR(INDEX(Gabarito!$M:$M,MATCH($A2,Gabarito!$A:$A,0)),"") | C2: =IF('Revisor B'!G2<>"",'Revisor B'!G2,IF('Revisor B'!F2="","não preenchido",IF(ABS(N('Revisor B'!F2)-N(INDEX(Gabarito!$B:$B,MATCH($A2,Gabarito!$A:$A,0))))<=1,"confere","diverge"))) | D2: =IF('Revisor B'!I2<>"",'Revisor B'!I2,IF('Revisor B'!H2="","não preenchido",IF(ABS(N('Revisor B'!H2)-N(INDEX(Gabarito!$C:$C,MATCH($A2,Gabarito!$A:$A,0))))<=1,"confere","diverge"))) | E2: =IF('Revisor B'!K2<>"",'Revisor B'!K2,IF('Revisor B'!J2="","não preenchido",IF(LOWER(TRIM('Revisor B'!J2))=LOWER(TRIM(INDEX(Gabarito!$D:$D,MATCH($A2,Gabarito!$A:$A,0)))),"confere","diverge"))) | F2: =IF('Revisor B'!M2<>"",'Revisor B'!M2,IF('Revisor B'!L2="","não preenchido",IF(LOWER(TRIM('Revisor B'!L2))=LOWER(TRIM(INDEX(Gabarito!$E:$E,MATCH($A2,Gabarito!$A:$A,0)))),"confere","diverge"))) | G2: =IF('Revisor B'!O2<>"",'Revisor B'!O2,IF('Revisor B'!N2="","não preenchido",IF(LOWER(TRIM('Revisor B'!N2))=LOWER(TRIM(INDEX(Gabarito!$F:$F,MATCH($A2,Gabarito!$A:$A,0)))),"confere","diverge"))) | H2: =IF('Revisor B'!Q2<>"",'Revisor B'!Q2,IF('Revisor B'!P2="","não preenchido",IF(LOWER(TRIM('Revisor B'!P2))=LOWER(TRIM(INDEX(Gabarito!$G:$G,MATCH($A2,Gabarito!$A:$A,0)))),"confere","diverge"))) | I2: =IF('Revisor B'!S2<>"",'Revisor B'!S2,IF('Revisor B'!R2="","não preenchido",IF(LOWER(TRIM('Revisor B'!R2))=LOWER(TRIM(INDEX(Gabarito!$H:$H,MATCH($A2,Gabarito!$A:$A,0)))),"confere","diverge"))) | J2: =IF('Revisor B'!U2<>"",'Revisor B'!U2,IF('Revisor B'!T2="","não preenchido",IF(LOWER(TRIM('Revisor B'!T2))=LOWER(TRIM(INDEX(Gabarito!$I:$I,MATCH($A2,Gabarito!$A:$A,0)))),"confere","diverge"))) | K2: =IF('Revisor B'!W2<>"",'Revisor B'!W2,IF('Revisor B'!V2="","não preenchido",IF(LOWER(TRIM('Revisor B'!V2))=LOWER(TRIM(INDEX(Gabarito!$J:$J,MATCH($A2,Gabarito!$A:$A,0)))),"confere","diverge"))) | L2: =IF('Revisor B'!AB2="","não preenchido",'Revisor B'!AB2) | M2: =IF('Revisor B'!AC2="","não preenchido",'Revisor B'!AC2) | N2: =COUNTIF(C2:K2,"diverge") | O2: =IF(COUNTIF(C2:K2,"não preenchido")=9,"não preenchido",IF(N2>0,"diverge","confere")) | P2: =IFERROR(INDEX('Apuração A'!$C$2:$C$101,MATCH($A2,'Apuração A'!$A$2:$A$101,0)),"") | Q2: =IFERROR(INDEX('Apuração A'!$D$2:$D$101,MATCH($A2,'Apuração A'!$A$2:$A$101,0)),"") | R2: =IFERROR(INDEX('Apuração A'!$E$2:$E$101,MATCH($A2,'Apuração A'!$A$2:$A$101,0)),"") | S2: =IFERROR(INDEX('Apuração A'!$F$2:$F$101,MATCH($A2,'Apuração A'!$A$2:$A$101,0)),"") | T2: =IFERROR(INDEX('Apuração A'!$G$2:$G$101,MATCH($A2,'Apuração A'!$A$2:$A$101,0)),"") | U2: =IFERROR(INDEX('Apuração A'!$H$2:$H$101,MATCH($A2,'Apuração A'!$A$2:$A$101,0)),"") | V2: =IFERROR(INDEX('Apuração A'!$I$2:$I$101,MATCH($A2,'Apuração A'!$A$2:$A$101,0)),"") | W2: =IFERROR(INDEX('Apuração A'!$J$2:$J$101,MATCH($A2,'Apuração A'!$A$2:$A$101,0)),"") | X2: =IFERROR(INDEX('Apuração A'!$K$2:$K$101,MATCH($A2,'Apuração A'!$A$2:$A$101,0)),"")
A3: ='Revisor B'!A3 | B3: =IFERROR(INDEX(Gabarito!$M:$M,MATCH($A3,Gabarito!$A:$A,0)),"") | C3: =IF('Revisor B'!G3<>"",'Revisor B'!G3,IF('Revisor B'!F3="","não preenchido",IF(ABS(N('Revisor B'!F3)-N(INDEX(Gabarito!$B:$B,MATCH($A3,Gabarito!$A:$A,0))))<=1,"confere","diverge"))) | D3: =IF('Revisor B'!I3<>"",'Revisor B'!I3,IF('Revisor B'!H3="","não preenchido",IF(ABS(N('Revisor B'!H3)-N(INDEX(Gabarito!$C:$C,MATCH($A3,Gabarito!$A:$A,0))))<=1,"confere","diverge"))) | E3: =IF('Revisor B'!K3<>"",'Revisor B'!K3,IF('Revisor B'!J3="","não preenchido",IF(LOWER(TRIM('Revisor B'!J3))=LOWER(TRIM(INDEX(Gabarito!$D:$D,MATCH($A3,Gabarito!$A:$A,0)))),"confere","diverge"))) | F3: =IF('Revisor B'!M3<>"",'Revisor B'!M3,IF('Revisor B'!L3="","não preenchido",IF(LOWER(TRIM('Revisor B'!L3))=LOWER(TRIM(INDEX(Gabarito!$E:$E,MATCH($A3,Gabarito!$A:$A,0)))),"confere","diverge"))) | G3: =IF('Revisor B'!O3<>"",'Revisor B'!O3,IF('Revisor B'!N3="","não preenchido",IF(LOWER(TRIM('Revisor B'!N3))=LOWER(TRIM(INDEX(Gabarito!$F:$F,MATCH($A3,Gabarito!$A:$A,0)))),"confere","diverge"))) | H3: =IF('Revisor B'!Q3<>"",'Revisor B'!Q3,IF('Revisor B'!P3="","não preenchido",IF(LOWER(TRIM('Revisor B'!P3))=LOWER(TRIM(INDEX(Gabarito!$G:$G,MATCH($A3,Gabarito!$A:$A,0)))),"confere","diverge"))) | I3: =IF('Revisor B'!S3<>"",'Revisor B'!S3,IF('Revisor B'!R3="","não preenchido",IF(LOWER(TRIM('Revisor B'!R3))=LOWER(TRIM(INDEX(Gabarito!$H:$H,MATCH($A3,Gabarito!$A:$A,0)))),"confere","diverge"))) | J3: =IF('Revisor B'!U3<>"",'Revisor B'!U3,IF('Revisor B'!T3="","não preenchido",IF(LOWER(TRIM('Revisor B'!T3))=LOWER(TRIM(INDEX(Gabarito!$I:$I,MATCH($A3,Gabarito!$A:$A,0)))),"confere","diverge"))) | K3: =IF('Revisor B'!W3<>"",'Revisor B'!W3,IF('Revisor B'!V3="","não preenchido",IF(LOWER(TRIM('Revisor B'!V3))=LOWER(TRIM(INDEX(Gabarito!$J:$J,MATCH($A3,Gabarito!$A:$A,0)))),"confere","diverge"))) | L3: =IF('Revisor B'!AB3="","não preenchido",'Revisor B'!AB3) | M3: =IF('Revisor B'!AC3="","não preenchido",'Revisor B'!AC3) | N3: =COUNTIF(C3:K3,"diverge") | O3: =IF(COUNTIF(C3:K3,"não preenchido")=9,"não preenchido",IF(N3>0,"diverge","confere")) | P3: =IFERROR(INDEX('Apuração A'!$C$2:$C$101,MATCH($A3,'Apuração A'!$A$2:$A$101,0)),"") | Q3: =IFERROR(INDEX('Apuração A'!$D$2:$D$101,MATCH($A3,'Apuração A'!$A$2:$A$101,0)),"") | R3: =IFERROR(INDEX('Apuração A'!$E$2:$E$101,MATCH($A3,'Apuração A'!$A$2:$A$101,0)),"") | S3: =IFERROR(INDEX('Apuração A'!$F$2:$F$101,MATCH($A3,'Apuração A'!$A$2:$A$101,0)),"") | T3: =IFERROR(INDEX('Apuração A'!$G$2:$G$101,MATCH($A3,'Apuração A'!$A$2:$A$101,0)),"") | U3: =IFERROR(INDEX('Apuração A'!$H$2:$H$101,MATCH($A3,'Apuração A'!$A$2:$A$101,0)),"") | V3: =IFERROR(INDEX('Apuração A'!$I$2:$I$101,MATCH($A3,'Apuração A'!$A$2:$A$101,0)),"") | W3: =IFERROR(INDEX('Apuração A'!$J$2:$J$101,MATCH($A3,'Apuração A'!$A$2:$A$101,0)),"") | X3: =IFERROR(INDEX('Apuração A'!$K$2:$K$101,MATCH($A3,'Apuração A'!$A$2:$A$101,0)),"")
A4: ='Revisor B'!A4 | B4: =IFERROR(INDEX(Gabarito!$M:$M,MATCH($A4,Gabarito!$A:$A,0)),"") | C4: =IF('Revisor B'!G4<>"",'Revisor B'!G4,IF('Revisor B'!F4="","não preenchido",IF(ABS(N('Revisor B'!F4)-N(INDEX(Gabarito!$B:$B,MATCH($A4,Gabarito!$A:$A,0))))<=1,"confere","diverge"))) | D4: =IF('Revisor B'!I4<>"",'Revisor B'!I4,IF('Revisor B'!H4="","não preenchido",IF(ABS(N('Revisor B'!H4)-N(INDEX(Gabarito!$C:$C,MATCH($A4,Gabarito!$A:$A,0))))<=1,"confere","diverge"))) | E4: =IF('Revisor B'!K4<>"",'Revisor B'!K4,IF('Revisor B'!J4="","não preenchido",IF(LOWER(TRIM('Revisor B'!J4))=LOWER(TRIM(INDEX(Gabarito!$D:$D,MATCH($A4,Gabarito!$A:$A,0)))),"confere","diverge"))) | F4: =IF('Revisor B'!M4<>"",'Revisor B'!M4,IF('Revisor B'!L4="","não preenchido",IF(LOWER(TRIM('Revisor B'!L4))=LOWER(TRIM(INDEX(Gabarito!$E:$E,MATCH($A4,Gabarito!$A:$A,0)))),"confere","diverge"))) | G4: =IF('Revisor B'!O4<>"",'Revisor B'!O4,IF('Revisor B'!N4="","não preenchido",IF(LOWER(TRIM('Revisor B'!N4))=LOWER(TRIM(INDEX(Gabarito!$F:$F,MATCH($A4,Gabarito!$A:$A,0)))),"confere","diverge"))) | H4: =IF('Revisor B'!Q4<>"",'Revisor B'!Q4,IF('Revisor B'!P4="","não preenchido",IF(LOWER(TRIM('Revisor B'!P4))=LOWER(TRIM(INDEX(Gabarito!$G:$G,MATCH($A4,Gabarito!$A:$A,0)))),"confere","diverge"))) | I4: =IF('Revisor B'!S4<>"",'Revisor B'!S4,IF('Revisor B'!R4="","não preenchido",IF(LOWER(TRIM('Revisor B'!R4))=LOWER(TRIM(INDEX(Gabarito!$H:$H,MATCH($A4,Gabarito!$A:$A,0)))),"confere","diverge"))) | J4: =IF('Revisor B'!U4<>"",'Revisor B'!U4,IF('Revisor B'!T4="","não preenchido",IF(LOWER(TRIM('Revisor B'!T4))=LOWER(TRIM(INDEX(Gabarito!$I:$I,MATCH($A4,Gabarito!$A:$A,0)))),"confere","diverge"))) | K4: =IF('Revisor B'!W4<>"",'Revisor B'!W4,IF('Revisor B'!V4="","não preenchido",IF(LOWER(TRIM('Revisor B'!V4))=LOWER(TRIM(INDEX(Gabarito!$J:$J,MATCH($A4,Gabarito!$A:$A,0)))),"confere","diverge"))) | L4: =IF('Revisor B'!AB4="","não preenchido",'Revisor B'!AB4) | M4: =IF('Revisor B'!AC4="","não preenchido",'Revisor B'!AC4) | N4: =COUNTIF(C4:K4,"diverge") | O4: =IF(COUNTIF(C4:K4,"não preenchido")=9,"não preenchido",IF(N4>0,"diverge","confere")) | P4: =IFERROR(INDEX('Apuração A'!$C$2:$C$101,MATCH($A4,'Apuração A'!$A$2:$A$101,0)),"") | Q4: =IFERROR(INDEX('Apuração A'!$D$2:$D$101,MATCH($A4,'Apuração A'!$A$2:$A$101,0)),"") | R4: =IFERROR(INDEX('Apuração A'!$E$2:$E$101,MATCH($A4,'Apuração A'!$A$2:$A$101,0)),"") | S4: =IFERROR(INDEX('Apuração A'!$F$2:$F$101,MATCH($A4,'Apuração A'!$A$2:$A$101,0)),"") | T4: =IFERROR(INDEX('Apuração A'!$G$2:$G$101,MATCH($A4,'Apuração A'!$A$2:$A$101,0)),"") | U4: =IFERROR(INDEX('Apuração A'!$H$2:$H$101,MATCH($A4,'Apuração A'!$A$2:$A$101,0)),"") | V4: =IFERROR(INDEX('Apuração A'!$I$2:$I$101,MATCH($A4,'Apuração A'!$A$2:$A$101,0)),"") | W4: =IFERROR(INDEX('Apuração A'!$J$2:$J$101,MATCH($A4,'Apuração A'!$A$2:$A$101,0)),"") | X4: =IFERROR(INDEX('Apuração A'!$K$2:$K$101,MATCH($A4,'Apuração A'!$A$2:$A$101,0)),"")
A5: ='Revisor B'!A5 | B5: =IFERROR(INDEX(Gabarito!$M:$M,MATCH($A5,Gabarito!$A:$A,0)),"") | C5: =IF('Revisor B'!G5<>"",'Revisor B'!G5,IF('Revisor B'!F5="","não preenchido",IF(ABS(N('Revisor B'!F5)-N(INDEX(Gabarito!$B:$B,MATCH($A5,Gabarito!$A:$A,0))))<=1,"confere","diverge"))) | D5: =IF('Revisor B'!I5<>"",'Revisor B'!I5,IF('Revisor B'!H5="","não preenchido",IF(ABS(N('Revisor B'!H5)-N(INDEX(Gabarito!$C:$C,MATCH($A5,Gabarito!$A:$A,0))))<=1,"confere","diverge"))) | E5: =IF('Revisor B'!K5<>"",'Revisor B'!K5,IF('Revisor B'!J5="","não preenchido",IF(LOWER(TRIM('Revisor B'!J5))=LOWER(TRIM(INDEX(Gabarito!$D:$D,MATCH($A5,Gabarito!$A:$A,0)))),"confere","diverge"))) | F5: =IF('Revisor B'!M5<>"",'Revisor B'!M5,IF('Revisor B'!L5="","não preenchido",IF(LOWER(TRIM('Revisor B'!L5))=LOWER(TRIM(INDEX(Gabarito!$E:$E,MATCH($A5,Gabarito!$A:$A,0)))),"confere","diverge"))) | G5: =IF('Revisor B'!O5<>"",'Revisor B'!O5,IF('Revisor B'!N5="","não preenchido",IF(LOWER(TRIM('Revisor B'!N5))=LOWER(TRIM(INDEX(Gabarito!$F:$F,MATCH($A5,Gabarito!$A:$A,0)))),"confere","diverge"))) | H5: =IF('Revisor B'!Q5<>"",'Revisor B'!Q5,IF('Revisor B'!P5="","não preenchido",IF(LOWER(TRIM('Revisor B'!P5))=LOWER(TRIM(INDEX(Gabarito!$G:$G,MATCH($A5,Gabarito!$A:$A,0)))),"confere","diverge"))) | I5: =IF('Revisor B'!S5<>"",'Revisor B'!S5,IF('Revisor B'!R5="","não preenchido",IF(LOWER(TRIM('Revisor B'!R5))=LOWER(TRIM(INDEX(Gabarito!$H:$H,MATCH($A5,Gabarito!$A:$A,0)))),"confere","diverge"))) | J5: =IF('Revisor B'!U5<>"",'Revisor B'!U5,IF('Revisor B'!T5="","não preenchido",IF(LOWER(TRIM('Revisor B'!T5))=LOWER(TRIM(INDEX(Gabarito!$I:$I,MATCH($A5,Gabarito!$A:$A,0)))),"confere","diverge"))) | K5: =IF('Revisor B'!W5<>"",'Revisor B'!W5,IF('Revisor B'!V5="","não preenchido",IF(LOWER(TRIM('Revisor B'!V5))=LOWER(TRIM(INDEX(Gabarito!$J:$J,MATCH($A5,Gabarito!$A:$A,0)))),"confere","diverge"))) | L5: =IF('Revisor B'!AB5="","não preenchido",'Revisor B'!AB5) | M5: =IF('Revisor B'!AC5="","não preenchido",'Revisor B'!AC5) | N5: =COUNTIF(C5:K5,"diverge") | O5: =IF(COUNTIF(C5:K5,"não preenchido")=9,"não preenchido",IF(N5>0,"diverge","confere")) | P5: =IFERROR(INDEX('Apuração A'!$C$2:$C$101,MATCH($A5,'Apuração A'!$A$2:$A$101,0)),"") | Q5: =IFERROR(INDEX('Apuração A'!$D$2:$D$101,MATCH($A5,'Apuração A'!$A$2:$A$101,0)),"") | R5: =IFERROR(INDEX('Apuração A'!$E$2:$E$101,MATCH($A5,'Apuração A'!$A$2:$A$101,0)),"") | S5: =IFERROR(INDEX('Apuração A'!$F$2:$F$101,MATCH($A5,'Apuração A'!$A$2:$A$101,0)),"") | T5: =IFERROR(INDEX('Apuração A'!$G$2:$G$101,MATCH($A5,'Apuração A'!$A$2:$A$101,0)),"") | U5: =IFERROR(INDEX('Apuração A'!$H$2:$H$101,MATCH($A5,'Apuração A'!$A$2:$A$101,0)),"") | V5: =IFERROR(INDEX('Apuração A'!$I$2:$I$101,MATCH($A5,'Apuração A'!$A$2:$A$101,0)),"") | W5: =IFERROR(INDEX('Apuração A'!$J$2:$J$101,MATCH($A5,'Apuração A'!$A$2:$A$101,0)),"") | X5: =IFERROR(INDEX('Apuração A'!$K$2:$K$101,MATCH($A5,'Apuração A'!$A$2:$A$101,0)),"")
A6: ='Revisor B'!A6 | B6: =IFERROR(INDEX(Gabarito!$M:$M,MATCH($A6,Gabarito!$A:$A,0)),"") | C6: =IF('Revisor B'!G6<>"",'Revisor B'!G6,IF('Revisor B'!F6="","não preenchido",IF(ABS(N('Revisor B'!F6)-N(INDEX(Gabarito!$B:$B,MATCH($A6,Gabarito!$A:$A,0))))<=1,"confere","diverge"))) | D6: =IF('Revisor B'!I6<>"",'Revisor B'!I6,IF('Revisor B'!H6="","não preenchido",IF(ABS(N('Revisor B'!H6)-N(INDEX(Gabarito!$C:$C,MATCH($A6,Gabarito!$A:$A,0))))<=1,"confere","diverge"))) | E6: =IF('Revisor B'!K6<>"",'Revisor B'!K6,IF('Revisor B'!J6="","não preenchido",IF(LOWER(TRIM('Revisor B'!J6))=LOWER(TRIM(INDEX(Gabarito!$D:$D,MATCH($A6,Gabarito!$A:$A,0)))),"confere","diverge"))) | F6: =IF('Revisor B'!M6<>"",'Revisor B'!M6,IF('Revisor B'!L6="","não preenchido",IF(LOWER(TRIM('Revisor B'!L6))=LOWER(TRIM(INDEX(Gabarito!$E:$E,MATCH($A6,Gabarito!$A:$A,0)))),"confere","diverge"))) | G6: =IF('Revisor B'!O6<>"",'Revisor B'!O6,IF('Revisor B'!N6="","não preenchido",IF(LOWER(TRIM('Revisor B'!N6))=LOWER(TRIM(INDEX(Gabarito!$F:$F,MATCH($A6,Gabarito!$A:$A,0)))),"confere","diverge"))) | H6: =IF('Revisor B'!Q6<>"",'Revisor B'!Q6,IF('Revisor B'!P6="","não preenchido",IF(LOWER(TRIM('Revisor B'!P6))=LOWER(TRIM(INDEX(Gabarito!$G:$G,MATCH($A6,Gabarito!$A:$A,0)))),"confere","diverge"))) | I6: =IF('Revisor B'!S6<>"",'Revisor B'!S6,IF('Revisor B'!R6="","não preenchido",IF(LOWER(TRIM('Revisor B'!R6))=LOWER(TRIM(INDEX(Gabarito!$H:$H,MATCH($A6,Gabarito!$A:$A,0)))),"confere","diverge"))) | J6: =IF('Revisor B'!U6<>"",'Revisor B'!U6,IF('Revisor B'!T6="","não preenchido",IF(LOWER(TRIM('Revisor B'!T6))=LOWER(TRIM(INDEX(Gabarito!$I:$I,MATCH($A6,Gabarito!$A:$A,0)))),"confere","diverge"))) | K6: =IF('Revisor B'!W6<>"",'Revisor B'!W6,IF('Revisor B'!V6="","não preenchido",IF(LOWER(TRIM('Revisor B'!V6))=LOWER(TRIM(INDEX(Gabarito!$J:$J,MATCH($A6,Gabarito!$A:$A,0)))),"confere","diverge"))) | L6: =IF('Revisor B'!AB6="","não preenchido",'Revisor B'!AB6) | M6: =IF('Revisor B'!AC6="","não preenchido",'Revisor B'!AC6) | N6: =COUNTIF(C6:K6,"diverge") | O6: =IF(COUNTIF(C6:K6,"não preenchido")=9,"não preenchido",IF(N6>0,"diverge","confere")) | P6: =IFERROR(INDEX('Apuração A'!$C$2:$C$101,MATCH($A6,'Apuração A'!$A$2:$A$101,0)),"") | Q6: =IFERROR(INDEX('Apuração A'!$D$2:$D$101,MATCH($A6,'Apuração A'!$A$2:$A$101,0)),"") | R6: =IFERROR(INDEX('Apuração A'!$E$2:$E$101,MATCH($A6,'Apuração A'!$A$2:$A$101,0)),"") | S6: =IFERROR(INDEX('Apuração A'!$F$2:$F$101,MATCH($A6,'Apuração A'!$A$2:$A$101,0)),"") | T6: =IFERROR(INDEX('Apuração A'!$G$2:$G$101,MATCH($A6,'Apuração A'!$A$2:$A$101,0)),"") | U6: =IFERROR(INDEX('Apuração A'!$H$2:$H$101,MATCH($A6,'Apuração A'!$A$2:$A$101,0)),"") | V6: =IFERROR(INDEX('Apuração A'!$I$2:$I$101,MATCH($A6,'Apuração A'!$A$2:$A$101,0)),"") | W6: =IFERROR(INDEX('Apuração A'!$J$2:$J$101,MATCH($A6,'Apuração A'!$A$2:$A$101,0)),"") | X6: =IFERROR(INDEX('Apuração A'!$K$2:$K$101,MATCH($A6,'Apuração A'!$A$2:$A$101,0)),"")
A7: ='Revisor B'!A7 | B7: =IFERROR(INDEX(Gabarito!$M:$M,MATCH($A7,Gabarito!$A:$A,0)),"") | C7: =IF('Revisor B'!G7<>"",'Revisor B'!G7,IF('Revisor B'!F7="","não preenchido",IF(ABS(N('Revisor B'!F7)-N(INDEX(Gabarito!$B:$B,MATCH($A7,Gabarito!$A:$A,0))))<=1,"confere","diverge"))) | D7: =IF('Revisor B'!I7<>"",'Revisor B'!I7,IF('Revisor B'!H7="","não preenchido",IF(ABS(N('Revisor B'!H7)-N(INDEX(Gabarito!$C:$C,MATCH($A7,Gabarito!$A:$A,0))))<=1,"confere","diverge"))) | E7: =IF('Revisor B'!K7<>"",'Revisor B'!K7,IF('Revisor B'!J7="","não preenchido",IF(LOWER(TRIM('Revisor B'!J7))=LOWER(TRIM(INDEX(Gabarito!$D:$D,MATCH($A7,Gabarito!$A:$A,0)))),"confere","diverge"))) | F7: =IF('Revisor B'!M7<>"",'Revisor B'!M7,IF('Revisor B'!L7="","não preenchido",IF(LOWER(TRIM('Revisor B'!L7))=LOWER(TRIM(INDEX(Gabarito!$E:$E,MATCH($A7,Gabarito!$A:$A,0)))),"confere","diverge"))) | G7: =IF('Revisor B'!O7<>"",'Revisor B'!O7,IF('Revisor B'!N7="","não preenchido",IF(LOWER(TRIM('Revisor B'!N7))=LOWER(TRIM(INDEX(Gabarito!$F:$F,MATCH($A7,Gabarito!$A:$A,0)))),"confere","diverge"))) | H7: =IF('Revisor B'!Q7<>"",'Revisor B'!Q7,IF('Revisor B'!P7="","não preenchido",IF(LOWER(TRIM('Revisor B'!P7))=LOWER(TRIM(INDEX(Gabarito!$G:$G,MATCH($A7,Gabarito!$A:$A,0)))),"confere","diverge"))) | I7: =IF('Revisor B'!S7<>"",'Revisor B'!S7,IF('Revisor B'!R7="","não preenchido",IF(LOWER(TRIM('Revisor B'!R7))=LOWER(TRIM(INDEX(Gabarito!$H:$H,MATCH($A7,Gabarito!$A:$A,0)))),"confere","diverge"))) | J7: =IF('Revisor B'!U7<>"",'Revisor B'!U7,IF('Revisor B'!T7="","não preenchido",IF(LOWER(TRIM('Revisor B'!T7))=LOWER(TRIM(INDEX(Gabarito!$I:$I,MATCH($A7,Gabarito!$A:$A,0)))),"confere","diverge"))) | K7: =IF('Revisor B'!W7<>"",'Revisor B'!W7,IF('Revisor B'!V7="","não preenchido",IF(LOWER(TRIM('Revisor B'!V7))=LOWER(TRIM(INDEX(Gabarito!$J:$J,MATCH($A7,Gabarito!$A:$A,0)))),"confere","diverge"))) | L7: =IF('Revisor B'!AB7="","não preenchido",'Revisor B'!AB7) | M7: =IF('Revisor B'!AC7="","não preenchido",'Revisor B'!AC7) | N7: =COUNTIF(C7:K7,"diverge") | O7: =IF(COUNTIF(C7:K7,"não preenchido")=9,"não preenchido",IF(N7>0,"diverge","confere")) | P7: =IFERROR(INDEX('Apuração A'!$C$2:$C$101,MATCH($A7,'Apuração A'!$A$2:$A$101,0)),"") | Q7: =IFERROR(INDEX('Apuração A'!$D$2:$D$101,MATCH($A7,'Apuração A'!$A$2:$A$101,0)),"") | R7: =IFERROR(INDEX('Apuração A'!$E$2:$E$101,MATCH($A7,'Apuração A'!$A$2:$A$101,0)),"") | S7: =IFERROR(INDEX('Apuração A'!$F$2:$F$101,MATCH($A7,'Apuração A'!$A$2:$A$101,0)),"") | T7: =IFERROR(INDEX('Apuração A'!$G$2:$G$101,MATCH($A7,'Apuração A'!$A$2:$A$101,0)),"") | U7: =IFERROR(INDEX('Apuração A'!$H$2:$H$101,MATCH($A7,'Apuração A'!$A$2:$A$101,0)),"") | V7: =IFERROR(INDEX('Apuração A'!$I$2:$I$101,MATCH($A7,'Apuração A'!$A$2:$A$101,0)),"") | W7: =IFERROR(INDEX('Apuração A'!$J$2:$J$101,MATCH($A7,'Apuração A'!$A$2:$A$101,0)),"") | X7: =IFERROR(INDEX('Apuração A'!$K$2:$K$101,MATCH($A7,'Apuração A'!$A$2:$A$101,0)),"")
A8: ='Revisor B'!A8 | B8: =IFERROR(INDEX(Gabarito!$M:$M,MATCH($A8,Gabarito!$A:$A,0)),"") | C8: =IF('Revisor B'!G8<>"",'Revisor B'!G8,IF('Revisor B'!F8="","não preenchido",IF(ABS(N('Revisor B'!F8)-N(INDEX(Gabarito!$B:$B,MATCH($A8,Gabarito!$A:$A,0))))<=1,"confere","diverge"))) | D8: =IF('Revisor B'!I8<>"",'Revisor B'!I8,IF('Revisor B'!H8="","não preenchido",IF(ABS(N('Revisor B'!H8)-N(INDEX(Gabarito!$C:$C,MATCH($A8,Gabarito!$A:$A,0))))<=1,"confere","diverge"))) | E8: =IF('Revisor B'!K8<>"",'Revisor B'!K8,IF('Revisor B'!J8="","não preenchido",IF(LOWER(TRIM('Revisor B'!J8))=LOWER(TRIM(INDEX(Gabarito!$D:$D,MATCH($A8,Gabarito!$A:$A,0)))),"confere","diverge"))) | F8: =IF('Revisor B'!M8<>"",'Revisor B'!M8,IF('Revisor B'!L8="","não preenchido",IF(LOWER(TRIM('Revisor B'!L8))=LOWER(TRIM(INDEX(Gabarito!$E:$E,MATCH($A8,Gabarito!$A:$A,0)))),"confere","diverge"))) | G8: =IF('Revisor B'!O8<>"",'Revisor B'!O8,IF('Revisor B'!N8="","não preenchido",IF(LOWER(TRIM('Revisor B'!N8))=LOWER(TRIM(INDEX(Gabarito!$F:$F,MATCH($A8,Gabarito!$A:$A,0)))),"confere","diverge"))) | H8: =IF('Revisor B'!Q8<>"",'Revisor B'!Q8,IF('Revisor B'!P8="","não preenchido",IF(LOWER(TRIM('Revisor B'!P8))=LOWER(TRIM(INDEX(Gabarito!$G:$G,MATCH($A8,Gabarito!$A:$A,0)))),"confere","diverge"))) | I8: =IF('Revisor B'!S8<>"",'Revisor B'!S8,IF('Revisor B'!R8="","não preenchido",IF(LOWER(TRIM('Revisor B'!R8))=LOWER(TRIM(INDEX(Gabarito!$H:$H,MATCH($A8,Gabarito!$A:$A,0)))),"confere","diverge"))) | J8: =IF('Revisor B'!U8<>"",'Revisor B'!U8,IF('Revisor B'!T8="","não preenchido",IF(LOWER(TRIM('Revisor B'!T8))=LOWER(TRIM(INDEX(Gabarito!$I:$I,MATCH($A8,Gabarito!$A:$A,0)))),"confere","diverge"))) | K8: =IF('Revisor B'!W8<>"",'Revisor B'!W8,IF('Revisor B'!V8="","não preenchido",IF(LOWER(TRIM('Revisor B'!V8))=LOWER(TRIM(INDEX(Gabarito!$J:$J,MATCH($A8,Gabarito!$A:$A,0)))),"confere","diverge"))) | L8: =IF('Revisor B'!AB8="","não preenchido",'Revisor B'!AB8) | M8: =IF('Revisor B'!AC8="","não preenchido",'Revisor B'!AC8) | N8: =COUNTIF(C8:K8,"diverge") | O8: =IF(COUNTIF(C8:K8,"não preenchido")=9,"não preenchido",IF(N8>0,"diverge","confere")) | P8: =IFERROR(INDEX('Apuração A'!$C$2:$C$101,MATCH($A8,'Apuração A'!$A$2:$A$101,0)),"") | Q8: =IFERROR(INDEX('Apuração A'!$D$2:$D$101,MATCH($A8,'Apuração A'!$A$2:$A$101,0)),"") | R8: =IFERROR(INDEX('Apuração A'!$E$2:$E$101,MATCH($A8,'Apuração A'!$A$2:$A$101,0)),"") | S8: =IFERROR(INDEX('Apuração A'!$F$2:$F$101,MATCH($A8,'Apuração A'!$A$2:$A$101,0)),"") | T8: =IFERROR(INDEX('Apuração A'!$G$2:$G$101,MATCH($A8,'Apuração A'!$A$2:$A$101,0)),"") | U8: =IFERROR(INDEX('Apuração A'!$H$2:$H$101,MATCH($A8,'Apuração A'!$A$2:$A$101,0)),"") | V8: =IFERROR(INDEX('Apuração A'!$I$2:$I$101,MATCH($A8,'Apuração A'!$A$2:$A$101,0)),"") | W8: =IFERROR(INDEX('Apuração A'!$J$2:$J$101,MATCH($A8,'Apuração A'!$A$2:$A$101,0)),"") | X8: =IFERROR(INDEX('Apuração A'!$K$2:$K$101,MATCH($A8,'Apuração A'!$A$2:$A$101,0)),"")
A9: ='Revisor B'!A9 | B9: =IFERROR(INDEX(Gabarito!$M:$M,MATCH($A9,Gabarito!$A:$A,0)),"") | C9: =IF('Revisor B'!G9<>"",'Revisor B'!G9,IF('Revisor B'!F9="","não preenchido",IF(ABS(N('Revisor B'!F9)-N(INDEX(Gabarito!$B:$B,MATCH($A9,Gabarito!$A:$A,0))))<=1,"confere","diverge"))) | D9: =IF('Revisor B'!I9<>"",'Revisor B'!I9,IF('Revisor B'!H9="","não preenchido",IF(ABS(N('Revisor B'!H9)-N(INDEX(Gabarito!$C:$C,MATCH($A9,Gabarito!$A:$A,0))))<=1,"confere","diverge"))) | E9: =IF('Revisor B'!K9<>"",'Revisor B'!K9,IF('Revisor B'!J9="","não preenchido",IF(LOWER(TRIM('Revisor B'!J9))=LOWER(TRIM(INDEX(Gabarito!$D:$D,MATCH($A9,Gabarito!$A:$A,0)))),"confere","diverge"))) | F9: =IF('Revisor B'!M9<>"",'Revisor B'!M9,IF('Revisor B'!L9="","não preenchido",IF(LOWER(TRIM('Revisor B'!L9))=LOWER(TRIM(INDEX(Gabarito!$E:$E,MATCH($A9,Gabarito!$A:$A,0)))),"confere","diverge"))) | G9: =IF('Revisor B'!O9<>"",'Revisor B'!O9,IF('Revisor B'!N9="","não preenchido",IF(LOWER(TRIM('Revisor B'!N9))=LOWER(TRIM(INDEX(Gabarito!$F:$F,MATCH($A9,Gabarito!$A:$A,0)))),"confere","diverge"))) | H9: =IF('Revisor B'!Q9<>"",'Revisor B'!Q9,IF('Revisor B'!P9="","não preenchido",IF(LOWER(TRIM('Revisor B'!P9))=LOWER(TRIM(INDEX(Gabarito!$G:$G,MATCH($A9,Gabarito!$A:$A,0)))),"confere","diverge"))) | I9: =IF('Revisor B'!S9<>"",'Revisor B'!S9,IF('Revisor B'!R9="","não preenchido",IF(LOWER(TRIM('Revisor B'!R9))=LOWER(TRIM(INDEX(Gabarito!$H:$H,MATCH($A9,Gabarito!$A:$A,0)))),"confere","diverge"))) | J9: =IF('Revisor B'!U9<>"",'Revisor B'!U9,IF('Revisor B'!T9="","não preenchido",IF(LOWER(TRIM('Revisor B'!T9))=LOWER(TRIM(INDEX(Gabarito!$I:$I,MATCH($A9,Gabarito!$A:$A,0)))),"confere","diverge"))) | K9: =IF('Revisor B'!W9<>"",'Revisor B'!W9,IF('Revisor B'!V9="","não preenchido",IF(LOWER(TRIM('Revisor B'!V9))=LOWER(TRIM(INDEX(Gabarito!$J:$J,MATCH($A9,Gabarito!$A:$A,0)))),"confere","diverge"))) | L9: =IF('Revisor B'!AB9="","não preenchido",'Revisor B'!AB9) | M9: =IF('Revisor B'!AC9="","não preenchido",'Revisor B'!AC9) | N9: =COUNTIF(C9:K9,"diverge") | O9: =IF(COUNTIF(C9:K9,"não preenchido")=9,"não preenchido",IF(N9>0,"diverge","confere")) | P9: =IFERROR(INDEX('Apuração A'!$C$2:$C$101,MATCH($A9,'Apuração A'!$A$2:$A$101,0)),"") | Q9: =IFERROR(INDEX('Apuração A'!$D$2:$D$101,MATCH($A9,'Apuração A'!$A$2:$A$101,0)),"") | R9: =IFERROR(INDEX('Apuração A'!$E$2:$E$101,MATCH($A9,'Apuração A'!$A$2:$A$101,0)),"") | S9: =IFERROR(INDEX('Apuração A'!$F$2:$F$101,MATCH($A9,'Apuração A'!$A$2:$A$101,0)),"") | T9: =IFERROR(INDEX('Apuração A'!$G$2:$G$101,MATCH($A9,'Apuração A'!$A$2:$A$101,0)),"") | U9: =IFERROR(INDEX('Apuração A'!$H$2:$H$101,MATCH($A9,'Apuração A'!$A$2:$A$101,0)),"") | V9: =IFERROR(INDEX('Apuração A'!$I$2:$I$101,MATCH($A9,'Apuração A'!$A$2:$A$101,0)),"") | W9: =IFERROR(INDEX('Apuração A'!$J$2:$J$101,MATCH($A9,'Apuração A'!$A$2:$A$101,0)),"") | X9: =IFERROR(INDEX('Apuração A'!$K$2:$K$101,MATCH($A9,'Apuração A'!$A$2:$A$101,0)),"")
A10: ='Revisor B'!A10 | B10: =IFERROR(INDEX(Gabarito!$M:$M,MATCH($A10,Gabarito!$A:$A,0)),"") | C10: =IF('Revisor B'!G10<>"",'Revisor B'!G10,IF('Revisor B'!F10="","não preenchido",IF(ABS(N('Revisor B'!F10)-N(INDEX(Gabarito!$B:$B,MATCH($A10,Gabarito!$A:$A,0))))<=1,"confere","diverge"))) | D10: =IF('Revisor B'!I10<>"",'Revisor B'!I10,IF('Revisor B'!H10="","não preenchido",IF(ABS(N('Revisor B'!H10)-N(INDEX(Gabarito!$C:$C,MATCH($A10,Gabarito!$A:$A,0))))<=1,"confere","diverge"))) | E10: =IF('Revisor B'!K10<>"",'Revisor B'!K10,IF('Revisor B'!J10="","não preenchido",IF(LOWER(TRIM('Revisor B'!J10))=LOWER(TRIM(INDEX(Gabarito!$D:$D,MATCH($A10,Gabarito!$A:$A,0)))),"confere","diverge"))) | F10: =IF('Revisor B'!M10<>"",'Revisor B'!M10,IF('Revisor B'!L10="","não preenchido",IF(LOWER(TRIM('Revisor B'!L10))=LOWER(TRIM(INDEX(Gabarito!$E:$E,MATCH($A10,Gabarito!$A:$A,0)))),"confere","diverge"))) | G10: =IF('Revisor B'!O10<>"",'Revisor B'!O10,IF('Revisor B'!N10="","não preenchido",IF(LOWER(TRIM('Revisor B'!N10))=LOWER(TRIM(INDEX(Gabarito!$F:$F,MATCH($A10,Gabarito!$A:$A,0)))),"confere","diverge"))) | H10: =IF('Revisor B'!Q10<>"",'Revisor B'!Q10,IF('Revisor B'!P10="","não preenchido",IF(LOWER(TRIM('Revisor B'!P10))=LOWER(TRIM(INDEX(Gabarito!$G:$G,MATCH($A10,Gabarito!$A:$A,0)))),"confere","diverge"))) | I10: =IF('Revisor B'!S10<>"",'Revisor B'!S10,IF('Revisor B'!R10="","não preenchido",IF(LOWER(TRIM('Revisor B'!R10))=LOWER(TRIM(INDEX(Gabarito!$H:$H,MATCH($A10,Gabarito!$A:$A,0)))),"confere","diverge"))) | J10: =IF('Revisor B'!U10<>"",'Revisor B'!U10,IF('Revisor B'!T10="","não preenchido",IF(LOWER(TRIM('Revisor B'!T10))=LOWER(TRIM(INDEX(Gabarito!$I:$I,MATCH($A10,Gabarito!$A:$A,0)))),"confere","diverge"))) | K10: =IF('Revisor B'!W10<>"",'Revisor B'!W10,IF('Revisor B'!V10="","não preenchido",IF(LOWER(TRIM('Revisor B'!V10))=LOWER(TRIM(INDEX(Gabarito!$J:$J,MATCH($A10,Gabarito!$A:$A,0)))),"confere","diverge"))) | L10: =IF('Revisor B'!AB10="","não preenchido",'Revisor B'!AB10) | M10: =IF('Revisor B'!AC10="","não preenchido",'Revisor B'!AC10) | N10: =COUNTIF(C10:K10,"diverge") | O10: =IF(COUNTIF(C10:K10,"não preenchido")=9,"não preenchido",IF(N10>0,"diverge","confere")) | P10: =IFERROR(INDEX('Apuração A'!$C$2:$C$101,MATCH($A10,'Apuração A'!$A$2:$A$101,0)),"") | Q10: =IFERROR(INDEX('Apuração A'!$D$2:$D$101,MATCH($A10,'Apuração A'!$A$2:$A$101,0)),"") | R10: =IFERROR(INDEX('Apuração A'!$E$2:$E$101,MATCH($A10,'Apuração A'!$A$2:$A$101,0)),"") | S10: =IFERROR(INDEX('Apuração A'!$F$2:$F$101,MATCH($A10,'Apuração A'!$A$2:$A$101,0)),"") | T10: =IFERROR(INDEX('Apuração A'!$G$2:$G$101,MATCH($A10,'Apuração A'!$A$2:$A$101,0)),"") | U10: =IFERROR(INDEX('Apuração A'!$H$2:$H$101,MATCH($A10,'Apuração A'!$A$2:$A$101,0)),"") | V10: =IFERROR(INDEX('Apuração A'!$I$2:$I$101,MATCH($A10,'Apuração A'!$A$2:$A$101,0)),"") | W10: =IFERROR(INDEX('Apuração A'!$J$2:$J$101,MATCH($A10,'Apuração A'!$A$2:$A$101,0)),"") | X10: =IFERROR(INDEX('Apuração A'!$K$2:$K$101,MATCH($A10,'Apuração A'!$A$2:$A$101,0)),"")
A11: ='Revisor B'!A11 | B11: =IFERROR(INDEX(Gabarito!$M:$M,MATCH($A11,Gabarito!$A:$A,0)),"") | C11: =IF('Revisor B'!G11<>"",'Revisor B'!G11,IF('Revisor B'!F11="","não preenchido",IF(ABS(N('Revisor B'!F11)-N(INDEX(Gabarito!$B:$B,MATCH($A11,Gabarito!$A:$A,0))))<=1,"confere","diverge"))) | D11: =IF('Revisor B'!I11<>"",'Revisor B'!I11,IF('Revisor B'!H11="","não preenchido",IF(ABS(N('Revisor B'!H11)-N(INDEX(Gabarito!$C:$C,MATCH($A11,Gabarito!$A:$A,0))))<=1,"confere","diverge"))) | E11: =IF('Revisor B'!K11<>"",'Revisor B'!K11,IF('Revisor B'!J11="","não preenchido",IF(LOWER(TRIM('Revisor B'!J11))=LOWER(TRIM(INDEX(Gabarito!$D:$D,MATCH($A11,Gabarito!$A:$A,0)))),"confere","diverge"))) | F11: =IF('Revisor B'!M11<>"",'Revisor B'!M11,IF('Revisor B'!L11="","não preenchido",IF(LOWER(TRIM('Revisor B'!L11))=LOWER(TRIM(INDEX(Gabarito!$E:$E,MATCH($A11,Gabarito!$A:$A,0)))),"confere","diverge"))) | G11: =IF('Revisor B'!O11<>"",'Revisor B'!O11,IF('Revisor B'!N11="","não preenchido",IF(LOWER(TRIM('Revisor B'!N11))=LOWER(TRIM(INDEX(Gabarito!$F:$F,MATCH($A11,Gabarito!$A:$A,0)))),"confere","diverge"))) | H11: =IF('Revisor B'!Q11<>"",'Revisor B'!Q11,IF('Revisor B'!P11="","não preenchido",IF(LOWER(TRIM('Revisor B'!P11))=LOWER(TRIM(INDEX(Gabarito!$G:$G,MATCH($A11,Gabarito!$A:$A,0)))),"confere","diverge"))) | I11: =IF('Revisor B'!S11<>"",'Revisor B'!S11,IF('Revisor B'!R11="","não preenchido",IF(LOWER(TRIM('Revisor B'!R11))=LOWER(TRIM(INDEX(Gabarito!$H:$H,MATCH($A11,Gabarito!$A:$A,0)))),"confere","diverge"))) | J11: =IF('Revisor B'!U11<>"",'Revisor B'!U11,IF('Revisor B'!T11="","não preenchido",IF(LOWER(TRIM('Revisor B'!T11))=LOWER(TRIM(INDEX(Gabarito!$I:$I,MATCH($A11,Gabarito!$A:$A,0)))),"confere","diverge"))) | K11: =IF('Revisor B'!W11<>"",'Revisor B'!W11,IF('Revisor B'!V11="","não preenchido",IF(LOWER(TRIM('Revisor B'!V11))=LOWER(TRIM(INDEX(Gabarito!$J:$J,MATCH($A11,Gabarito!$A:$A,0)))),"confere","diverge"))) | L11: =IF('Revisor B'!AB11="","não preenchido",'Revisor B'!AB11) | M11: =IF('Revisor B'!AC11="","não preenchido",'Revisor B'!AC11) | N11: =COUNTIF(C11:K11,"diverge") | O11: =IF(COUNTIF(C11:K11,"não preenchido")=9,"não preenchido",IF(N11>0,"diverge","confere")) | P11: =IFERROR(INDEX('Apuração A'!$C$2:$C$101,MATCH($A11,'Apuração A'!$A$2:$A$101,0)),"") | Q11: =IFERROR(INDEX('Apuração A'!$D$2:$D$101,MATCH($A11,'Apuração A'!$A$2:$A$101,0)),"") | R11: =IFERROR(INDEX('Apuração A'!$E$2:$E$101,MATCH($A11,'Apuração A'!$A$2:$A$101,0)),"") | S11: =IFERROR(INDEX('Apuração A'!$F$2:$F$101,MATCH($A11,'Apuração A'!$A$2:$A$101,0)),"") | T11: =IFERROR(INDEX('Apuração A'!$G$2:$G$101,MATCH($A11,'Apuração A'!$A$2:$A$101,0)),"") | U11: =IFERROR(INDEX('Apuração A'!$H$2:$H$101,MATCH($A11,'Apuração A'!$A$2:$A$101,0)),"") | V11: =IFERROR(INDEX('Apuração A'!$I$2:$I$101,MATCH($A11,'Apuração A'!$A$2:$A$101,0)),"") | W11: =IFERROR(INDEX('Apuração A'!$J$2:$J$101,MATCH($A11,'Apuração A'!$A$2:$A$101,0)),"") | X11: =IFERROR(INDEX('Apuração A'!$K$2:$K$101,MATCH($A11,'Apuração A'!$A$2:$A$101,0)),"")
A12: ='Revisor B'!A12 | B12: =IFERROR(INDEX(Gabarito!$M:$M,MATCH($A12,Gabarito!$A:$A,0)),"") | C12: =IF('Revisor B'!G12<>"",'Revisor B'!G12,IF('Revisor B'!F12="","não preenchido",IF(ABS(N('Revisor B'!F12)-N(INDEX(Gabarito!$B:$B,MATCH($A12,Gabarito!$A:$A,0))))<=1,"confere","diverge"))) | D12: =IF('Revisor B'!I12<>"",'Revisor B'!I12,IF('Revisor B'!H12="","não preenchido",IF(ABS(N('Revisor B'!H12)-N(INDEX(Gabarito!$C:$C,MATCH($A12,Gabarito!$A:$A,0))))<=1,"confere","diverge"))) | E12: =IF('Revisor B'!K12<>"",'Revisor B'!K12,IF('Revisor B'!J12="","não preenchido",IF(LOWER(TRIM('Revisor B'!J12))=LOWER(TRIM(INDEX(Gabarito!$D:$D,MATCH($A12,Gabarito!$A:$A,0)))),"confere","diverge"))) | F12: =IF('Revisor B'!M12<>"",'Revisor B'!M12,IF('Revisor B'!L12="","não preenchido",IF(LOWER(TRIM('Revisor B'!L12))=LOWER(TRIM(INDEX(Gabarito!$E:$E,MATCH($A12,Gabarito!$A:$A,0)))),"confere","diverge"))) | G12: =IF('Revisor B'!O12<>"",'Revisor B'!O12,IF('Revisor B'!N12="","não preenchido",IF(LOWER(TRIM('Revisor B'!N12))=LOWER(TRIM(INDEX(Gabarito!$F:$F,MATCH($A12,Gabarito!$A:$A,0)))),"confere","diverge"))) | H12: =IF('Revisor B'!Q12<>"",'Revisor B'!Q12,IF('Revisor B'!P12="","não preenchido",IF(LOWER(TRIM('Revisor B'!P12))=LOWER(TRIM(INDEX(Gabarito!$G:$G,MATCH($A12,Gabarito!$A:$A,0)))),"confere","diverge"))) | I12: =IF('Revisor B'!S12<>"",'Revisor B'!S12,IF('Revisor B'!R12="","não preenchido",IF(LOWER(TRIM('Revisor B'!R12))=LOWER(TRIM(INDEX(Gabarito!$H:$H,MATCH($A12,Gabarito!$A:$A,0)))),"confere","diverge"))) | J12: =IF('Revisor B'!U12<>"",'Revisor B'!U12,IF('Revisor B'!T12="","não preenchido",IF(LOWER(TRIM('Revisor B'!T12))=LOWER(TRIM(INDEX(Gabarito!$I:$I,MATCH($A12,Gabarito!$A:$A,0)))),"confere","diverge"))) | K12: =IF('Revisor B'!W12<>"",'Revisor B'!W12,IF('Revisor B'!V12="","não preenchido",IF(LOWER(TRIM('Revisor B'!V12))=LOWER(TRIM(INDEX(Gabarito!$J:$J,MATCH($A12,Gabarito!$A:$A,0)))),"confere","diverge"))) | L12: =IF('Revisor B'!AB12="","não preenchido",'Revisor B'!AB12) | M12: =IF('Revisor B'!AC12="","não preenchido",'Revisor B'!AC12) | N12: =COUNTIF(C12:K12,"diverge") | O12: =IF(COUNTIF(C12:K12,"não preenchido")=9,"não preenchido",IF(N12>0,"diverge","confere")) | P12: =IFERROR(INDEX('Apuração A'!$C$2:$C$101,MATCH($A12,'Apuração A'!$A$2:$A$101,0)),"") | Q12: =IFERROR(INDEX('Apuração A'!$D$2:$D$101,MATCH($A12,'Apuração A'!$A$2:$A$101,0)),"") | R12: =IFERROR(INDEX('Apuração A'!$E$2:$E$101,MATCH($A12,'Apuração A'!$A$2:$A$101,0)),"") | S12: =IFERROR(INDEX('Apuração A'!$F$2:$F$101,MATCH($A12,'Apuração A'!$A$2:$A$101,0)),"") | T12: =IFERROR(INDEX('Apuração A'!$G$2:$G$101,MATCH($A12,'Apuração A'!$A$2:$A$101,0)),"") | U12: =IFERROR(INDEX('Apuração A'!$H$2:$H$101,MATCH($A12,'Apuração A'!$A$2:$A$101,0)),"") | V12: =IFERROR(INDEX('Apuração A'!$I$2:$I$101,MATCH($A12,'Apuração A'!$A$2:$A$101,0)),"") | W12: =IFERROR(INDEX('Apuração A'!$J$2:$J$101,MATCH($A12,'Apuração A'!$A$2:$A$101,0)),"") | X12: =IFERROR(INDEX('Apuração A'!$K$2:$K$101,MATCH($A12,'Apuração A'!$A$2:$A$101,0)),"")
A13: ='Revisor B'!A13 | B13: =IFERROR(INDEX(Gabarito!$M:$M,MATCH($A13,Gabarito!$A:$A,0)),"") | C13: =IF('Revisor B'!G13<>"",'Revisor B'!G13,IF('Revisor B'!F13="","não preenchido",IF(ABS(N('Revisor B'!F13)-N(INDEX(Gabarito!$B:$B,MATCH($A13,Gabarito!$A:$A,0))))<=1,"confere","diverge"))) | D13: =IF('Revisor B'!I13<>"",'Revisor B'!I13,IF('Revisor B'!H13="","não preenchido",IF(ABS(N('Revisor B'!H13)-N(INDEX(Gabarito!$C:$C,MATCH($A13,Gabarito!$A:$A,0))))<=1,"confere","diverge"))) | E13: =IF('Revisor B'!K13<>"",'Revisor B'!K13,IF('Revisor B'!J13="","não preenchido",IF(LOWER(TRIM('Revisor B'!J13))=LOWER(TRIM(INDEX(Gabarito!$D:$D,MATCH($A13,Gabarito!$A:$A,0)))),"confere","diverge"))) | F13: =IF('Revisor B'!M13<>"",'Revisor B'!M13,IF('Revisor B'!L13="","não preenchido",IF(LOWER(TRIM('Revisor B'!L13))=LOWER(TRIM(INDEX(Gabarito!$E:$E,MATCH($A13,Gabarito!$A:$A,0)))),"confere","diverge"))) | G13: =IF('Revisor B'!O13<>"",'Revisor B'!O13,IF('Revisor B'!N13="","não preenchido",IF(LOWER(TRIM('Revisor B'!N13))=LOWER(TRIM(INDEX(Gabarito!$F:$F,MATCH($A13,Gabarito!$A:$A,0)))),"confere","diverge"))) | H13: =IF('Revisor B'!Q13<>"",'Revisor B'!Q13,IF('Revisor B'!P13="","não preenchido",IF(LOWER(TRIM('Revisor B'!P13))=LOWER(TRIM(INDEX(Gabarito!$G:$G,MATCH($A13,Gabarito!$A:$A,0)))),"confere","diverge"))) | I13: =IF('Revisor B'!S13<>"",'Revisor B'!S13,IF('Revisor B'!R13="","não preenchido",IF(LOWER(TRIM('Revisor B'!R13))=LOWER(TRIM(INDEX(Gabarito!$H:$H,MATCH($A13,Gabarito!$A:$A,0)))),"confere","diverge"))) | J13: =IF('Revisor B'!U13<>"",'Revisor B'!U13,IF('Revisor B'!T13="","não preenchido",IF(LOWER(TRIM('Revisor B'!T13))=LOWER(TRIM(INDEX(Gabarito!$I:$I,MATCH($A13,Gabarito!$A:$A,0)))),"confere","diverge"))) | K13: =IF('Revisor B'!W13<>"",'Revisor B'!W13,IF('Revisor B'!V13="","não preenchido",IF(LOWER(TRIM('Revisor B'!V13))=LOWER(TRIM(INDEX(Gabarito!$J:$J,MATCH($A13,Gabarito!$A:$A,0)))),"confere","diverge"))) | L13: =IF('Revisor B'!AB13="","não preenchido",'Revisor B'!AB13) | M13: =IF('Revisor B'!AC13="","não preenchido",'Revisor B'!AC13) | N13: =COUNTIF(C13:K13,"diverge") | O13: =IF(COUNTIF(C13:K13,"não preenchido")=9,"não preenchido",IF(N13>0,"diverge","confere")) | P13: =IFERROR(INDEX('Apuração A'!$C$2:$C$101,MATCH($A13,'Apuração A'!$A$2:$A$101,0)),"") | Q13: =IFERROR(INDEX('Apuração A'!$D$2:$D$101,MATCH($A13,'Apuração A'!$A$2:$A$101,0)),"") | R13: =IFERROR(INDEX('Apuração A'!$E$2:$E$101,MATCH($A13,'Apuração A'!$A$2:$A$101,0)),"") | S13: =IFERROR(INDEX('Apuração A'!$F$2:$F$101,MATCH($A13,'Apuração A'!$A$2:$A$101,0)),"") | T13: =IFERROR(INDEX('Apuração A'!$G$2:$G$101,MATCH($A13,'Apuração A'!$A$2:$A$101,0)),"") | U13: =IFERROR(INDEX('Apuração A'!$H$2:$H$101,MATCH($A13,'Apuração A'!$A$2:$A$101,0)),"") | V13: =IFERROR(INDEX('Apuração A'!$I$2:$I$101,MATCH($A13,'Apuração A'!$A$2:$A$101,0)),"") | W13: =IFERROR(INDEX('Apuração A'!$J$2:$J$101,MATCH($A13,'Apuração A'!$A$2:$A$101,0)),"") | X13: =IFERROR(INDEX('Apuração A'!$K$2:$K$101,MATCH($A13,'Apuração A'!$A$2:$A$101,0)),"")
... A21: ='Revisor B'!A21 | B21: =IFERROR(INDEX(Gabarito!$M:$M,MATCH($A21,Gabarito!$A:$A,0)),"") | C21: =IF('Revisor B'!G21<>"",'Revisor B'!G21,IF('Revisor B'!F21="","não preenchido",IF(ABS(N('Revisor B'!F21)-N(INDEX(Gabarito!$B:$B,MATCH($A21,Gabarito!$A:$A,0))))<=1,"confere","diverge"))) | D21: =IF('Revisor B'!I21<>"",'Revisor B'!I21,IF('Revisor B'!H21="","não preenchido",IF(ABS(N('Revisor B'!H21)-N(INDEX(Gabarito!$C:$C,MATCH($A21,Gabarito!$A:$A,0))))<=1,"confere","diverge"))) | E21: =IF('Revisor B'!K21<>"",'Revisor B'!K21,IF('Revisor B'!J21="","não preenchido",IF(LOWER(TRIM('Revisor B'!J21))=LOWER(TRIM(INDEX(Gabarito!$D:$D,MATCH($A21,Gabarito!$A:$A,0)))),"confere","diverge"))) | F21: =IF('Revisor B'!M21<>"",'Revisor B'!M21,IF('Revisor B'!L21="","não preenchido",IF(LOWER(TRIM('Revisor B'!L21))=LOWER(TRIM(INDEX(Gabarito!$E:$E,MATCH($A21,Gabarito!$A:$A,0)))),"confere","diverge"))) | G21: =IF('Revisor B'!O21<>"",'Revisor B'!O21,IF('Revisor B'!N21="","não preenchido",IF(LOWER(TRIM('Revisor B'!N21))=LOWER(TRIM(INDEX(Gabarito!$F:$F,MATCH($A21,Gabarito!$A:$A,0)))),"confere","diverge"))) | H21: =IF('Revisor B'!Q21<>"",'Revisor B'!Q21,IF('Revisor B'!P21="","não preenchido",IF(LOWER(TRIM('Revisor B'!P21))=LOWER(TRIM(INDEX(Gabarito!$G:$G,MATCH($A21,Gabarito!$A:$A,0)))),"confere","diverge"))) | I21: =IF('Revisor B'!S21<>"",'Revisor B'!S21,IF('Revisor B'!R21="","não preenchido",IF(LOWER(TRIM('Revisor B'!R21))=LOWER(TRIM(INDEX(Gabarito!$H:$H,MATCH($A21,Gabarito!$A:$A,0)))),"confere","diverge"))) | J21: =IF('Revisor B'!U21<>"",'Revisor B'!U21,IF('Revisor B'!T21="","não preenchido",IF(LOWER(TRIM('Revisor B'!T21))=LOWER(TRIM(INDEX(Gabarito!$I:$I,MATCH($A21,Gabarito!$A:$A,0)))),"confere","diverge"))) | K21: =IF('Revisor B'!W21<>"",'Revisor B'!W21,IF('Revisor B'!V21="","não preenchido",IF(LOWER(TRIM('Revisor B'!V21))=LOWER(TRIM(INDEX(Gabarito!$J:$J,MATCH($A21,Gabarito!$A:$A,0)))),"confere","diverge"))) | L21: =IF('Revisor B'!AB21="","não preenchido",'Revisor B'!AB21) | M21: =IF('Revisor B'!AC21="","não preenchido",'Revisor B'!AC21) | N21: =COUNTIF(C21:K21,"diverge") | O21: =IF(COUNTIF(C21:K21,"não preenchido")=9,"não preenchido",IF(N21>0,"diverge","confere")) | P21: =IFERROR(INDEX('Apuração A'!$C$2:$C$101,MATCH($A21,'Apuração A'!$A$2:$A$101,0)),"") | Q21: =IFERROR(INDEX('Apuração A'!$D$2:$D$101,MATCH($A21,'Apuração A'!$A$2:$A$101,0)),"") | R21: =IFERROR(INDEX('Apuração A'!$E$2:$E$101,MATCH($A21,'Apuração A'!$A$2:$A$101,0)),"") | S21: =IFERROR(INDEX('Apuração A'!$F$2:$F$101,MATCH($A21,'Apuração A'!$A$2:$A$101,0)),"") | T21: =IFERROR(INDEX('Apuração A'!$G$2:$G$101,MATCH($A21,'Apuração A'!$A$2:$A$101,0)),"") | U21: =IFERROR(INDEX('Apuração A'!$H$2:$H$101,MATCH($A21,'Apuração A'!$A$2:$A$101,0)),"") | V21: =IFERROR(INDEX('Apuração A'!$I$2:$I$101,MATCH($A21,'Apuração A'!$A$2:$A$101,0)),"") | W21: =IFERROR(INDEX('Apuração A'!$J$2:$J$101,MATCH($A21,'Apuração A'!$A$2:$A$101,0)),"") | X21: =IFERROR(INDEX('Apuração A'!$K$2:$K$101,MATCH($A21,'Apuração A'!$A$2:$A$101,0)),"")

Sheet Resumo
A1: Apuração da amostra — calculada pelas fórmulas desta planilha
A2: Intervalos exatos de Clopper-Pearson a 95% (BETA.INV). Mesma conta de scripts/auditoria/apurar.py, que é a referência.
A4: fichas preenchidas (Revisor A) | B4: =COUNTIF('Apuração A'!$O$2:$O$101,"confere")+COUNTIF('Apuração A'!$O$2:$O$101,"diverge")
A5: registros com divergência S1 | B5: =COUNTIF('Apuração A'!$O$2:$O$101,"diverge")
A6: taxa | B6: =IF(B4=0,"",B5/B4)
A7: IC 95% — inferior | B7: =IF(B4=0,"",IF(B5=0,0,_xlfn.BETA.INV(0.025,B5,B4-B5+1)))
A8: IC 95% — superior | B8: =IF(B4=0,"",IF(B5=B4,1,_xlfn.BETA.INV(0.975,B5+1,B4-B5)))
A10: Por campo (Revisor A)
A11: campo | B11: confere | C11: diverge | D11: fonte insuficiente | E11: juízo discutível | F11: não preenchido | G11: IC 95% sup. da divergência
A12: pena_min | B12: =COUNTIF('Apuração A'!$C$2:$C$101,"confere") | C12: =COUNTIF('Apuração A'!$C$2:$C$101,"diverge") | D12: =COUNTIF('Apuração A'!$C$2:$C$101,"fonte insuficiente") | E12: =COUNTIF('Apuração A'!$C$2:$C$101,"juízo discutível") | F12: =COUNTIF('Apuração A'!$C$2:$C$101,"não preenchido") | G12: =IF(B12+C12=0,"",IF(C12=B12+C12,1,_xlfn.BETA.INV(0.975,C12+1,B12)))
A13: pena_max | B13: =COUNTIF('Apuração A'!$D$2:$D$101,"confere") | C13: =COUNTIF('Apuração A'!$D$2:$D$101,"diverge") | D13: =COUNTIF('Apuração A'!$D$2:$D$101,"fonte insuficiente") | E13: =COUNTIF('Apuração A'!$D$2:$D$101,"juízo discutível") | F13: =COUNTIF('Apuração A'!$D$2:$D$101,"não preenchido") | G13: =IF(B13+C13=0,"",IF(C13=B13+C13,1,_xlfn.BETA.INV(0.975,C13+1,B13)))
A14: tipo_pena | B14: =COUNTIF('Apuração A'!$E$2:$E$101,"confere") | C14: =COUNTIF('Apuração A'!$E$2:$E$101,"diverge") | D14: =COUNTIF('Apuração A'!$E$2:$E$101,"fonte insuficiente") | E14: =COUNTIF('Apuração A'!$E$2:$E$101,"juízo discutível") | F14: =COUNTIF('Apuração A'!$E$2:$E$101,"não preenchido") | G14: =IF(B14+C14=0,"",IF(C14=B14+C14,1,_xlfn.BETA.INV(0.975,C14+1,B14)))
A15: hediondo | B15: =COUNTIF('Apuração A'!$F$2:$F$101,"confere") | C15: =COUNTIF('Apuração A'!$F$2:$F$101,"diverge") | D15: =COUNTIF('Apuração A'!$F$2:$F$101,"fonte insuficiente") | E15: =COUNTIF('Apuração A'!$F$2:$F$101,"juízo discutível") | F15: =COUNTIF('Apuração A'!$F$2:$F$101,"não preenchido") | G15: =IF(B15+C15=0,"",IF(C15=B15+C15,1,_xlfn.BETA.INV(0.975,C15+1,B15)))
A16: violencia | B16: =COUNTIF('Apuração A'!$G$2:$G$101,"confere") | C16: =COUNTIF('Apuração A'!$G$2:$G$101,"diverge") | D16: =COUNTIF('Apuração A'!$G$2:$G$101,"fonte insuficiente") | E16: =COUNTIF('Apuração A'!$G$2:$G$101,"juízo discutível") | F16: =COUNTIF('Apuração A'!$G$2:$G$101,"não preenchido") | G16: =IF(B16+C16=0,"",IF(C16=B16+C16,1,_xlfn.BETA.INV(0.975,C16+1,B16)))
A17: grave_ameaca | B17: =COUNTIF('Apuração A'!$H$2:$H$101,"confere") | C17: =COUNTIF('Apuração A'!$H$2:$H$101,"diverge") | D17: =COUNTIF('Apuração A'!$H$2:$H$101,"fonte insuficiente") | E17: =COUNTIF('Apuração A'!$H$2:$H$101,"juízo discutível") | F17: =COUNTIF('Apuração A'!$H$2:$H$101,"não preenchido") | G17: =IF(B17+C17=0,"",IF(C17=B17+C17,1,_xlfn.BETA.INV(0.975,C17+1,B17)))
A18: elemento | B18: =COUNTIF('Apuração A'!$I$2:$I$101,"confere") | C18: =COUNTIF('Apuração A'!$I$2:$I$101,"diverge") | D18: =COUNTIF('Apuração A'!$I$2:$I$101,"fonte insuficiente") | E18: =COUNTIF('Apuração A'!$I$2:$I$101,"juízo discutível") | F18: =COUNTIF('Apuração A'!$I$2:$I$101,"não preenchido") | G18: =IF(B18+C18=0,"",IF(C18=B18+C18,1,_xlfn.BETA.INV(0.975,C18+1,B18)))
A19: tentativa | B19: =COUNTIF('Apuração A'!$J$2:$J$101,"confere") | C19: =COUNTIF('Apuração A'!$J$2:$J$101,"diverge") | D19: =COUNTIF('Apuração A'!$J$2:$J$101,"fonte insuficiente") | E19: =COUNTIF('Apuração A'!$J$2:$J$101,"juízo discutível") | F19: =COUNTIF('Apuração A'!$J$2:$J$101,"não preenchido") | G19: =IF(B19+C19=0,"",IF(C19=B19+C19,1,_xlfn.BETA.INV(0.975,C19+1,B19)))
A20: acao | B20: =COUNTIF('Apuração A'!$K$2:$K$101,"confere") | C20: =COUNTIF('Apuração A'!$K$2:$K$101,"diverge") | D20: =COUNTIF('Apuração A'!$K$2:$K$101,"fonte insuficiente") | E20: =COUNTIF('Apuração A'!$K$2:$K$101,"juízo discutível") | F20: =COUNTIF('Apuração A'!$K$2:$K$101,"não preenchido") | G20: =IF(B20+C20=0,"",IF(C20=B20+C20,1,_xlfn.BETA.INV(0.975,C20+1,B20)))
A21: nome | B21: =COUNTIF('Apuração A'!$L$2:$L$101,"confere") | C21: =COUNTIF('Apuração A'!$L$2:$L$101,"diverge") | D21: =COUNTIF('Apuração A'!$L$2:$L$101,"fonte insuficiente") | E21: =COUNTIF('Apuração A'!$L$2:$L$101,"juízo discutível") | F21: =COUNTIF('Apuração A'!$L$2:$L$101,"não preenchido") | G21: =IF(B21+C21=0,"",IF(C21=B21+C21,1,_xlfn.BETA.INV(0.975,C21+1,B21)))
A22: vigência | B22: =COUNTIF('Apuração A'!$M$2:$M$101,"confere") | C22: =COUNTIF('Apuração A'!$M$2:$M$101,"diverge") | D22: =COUNTIF('Apuração A'!$M$2:$M$101,"fonte insuficiente") | E22: =COUNTIF('Apuração A'!$M$2:$M$101,"juízo discutível") | F22: =COUNTIF('Apuração A'!$M$2:$M$101,"não preenchido") | G22: =IF(B22+C22=0,"",IF(C22=B22+C22,1,_xlfn.BETA.INV(0.975,C22+1,B22)))
A24: Dupla conferência — κ de Cohen por campo (Revisor A × Revisor B, nas 20 fichas da dupla)
A25: campo | B25: n | C25: concordância bruta | D25: κ | E25: leitura
A26: pena_min | B26: 20 | C26: =SUMPRODUCT(--('Apuração B'!$P$2:$P$21='Apuração B'!$C$2:$C$21))/20 | D26: =IF((COUNTIF('Apuração B'!$C$2:$C$21,"confere")*COUNTIF('Apuração B'!$P$2:$P$21,"confere")+COUNTIF('Apuração B'!$C$2:$C$21,"diverge")*COUNTIF('Apuração B'!$P$2:$P$21,"diverge")+COUNTIF('Apuração B'!$C$2:$C$21,"fonte insuficiente")*COUNTIF('Apuração B'!$P$2:$P$21,"fonte insuficiente")+COUNTIF('Apuração B'!$C$2:$C$21,"juízo discutível")*COUNTIF('Apuração B'!$P$2:$P$21,"juízo discutível"))/20^2>=1,1,(SUMPRODUCT(--('Apuração B'!$P$2:$P$21='Apuração B'!$C$2:$C$21))/20-(COUNTIF('Apuração B'!$C$2:$C$21,"confere")*COUNTIF('Apuração B'!$P$2:$P$21,"confere")+COUNTIF('Apuração B'!$C$2:$C$21,"diverge")*COUNTIF('Apuração B'!$P$2:$P$21,"diverge")+COUNTIF('Apuração B'!$C$2:$C$21,"fonte insuficiente")*COUNTIF('Apuração B'!$P$2:$P$21,"fonte insuficiente")+COUNTIF('Apuração B'!$C$2:$C$21,"juízo discutível")*COUNTIF('Apuração B'!$P$2:$P$21,"juízo discutível"))/20^2)/(1-(COUNTIF('Apuração B'!$C$2:$C$21,"confere")*COUNTIF('Apuração B'!$P$2:$P$21,"confere")+COUNTIF('Apuração B'!$C$2:$C$21,"diverge")*COUNTIF('Apuração B'!$P$2:$P$21,"diverge")+COUNTIF('Apuração B'!$C$2:$C$21,"fonte insuficiente")*COUNTIF('Apuração B'!$P$2:$P$21,"fonte insuficiente")+COUNTIF('Apuração B'!$C$2:$C$21,"juízo discutível")*COUNTIF('Apuração B'!$P$2:$P$21,"juízo discutível"))/20^2)) | E26: =IF(D26>=0.8,"critério reproduzível",IF(D26>=0.6,"ler as discordâncias e escrever a regra","reconferir o campo nos 300"))
A27: pena_max | B27: 20 | C27: =SUMPRODUCT(--('Apuração B'!$Q$2:$Q$21='Apuração B'!$D$2:$D$21))/20 | D27: =IF((COUNTIF('Apuração B'!$D$2:$D$21,"confere")*COUNTIF('Apuração B'!$Q$2:$Q$21,"confere")+COUNTIF('Apuração B'!$D$2:$D$21,"diverge")*COUNTIF('Apuração B'!$Q$2:$Q$21,"diverge")+COUNTIF('Apuração B'!$D$2:$D$21,"fonte insuficiente")*COUNTIF('Apuração B'!$Q$2:$Q$21,"fonte insuficiente")+COUNTIF('Apuração B'!$D$2:$D$21,"juízo discutível")*COUNTIF('Apuração B'!$Q$2:$Q$21,"juízo discutível"))/20^2>=1,1,(SUMPRODUCT(--('Apuração B'!$Q$2:$Q$21='Apuração B'!$D$2:$D$21))/20-(COUNTIF('Apuração B'!$D$2:$D$21,"confere")*COUNTIF('Apuração B'!$Q$2:$Q$21,"confere")+COUNTIF('Apuração B'!$D$2:$D$21,"diverge")*COUNTIF('Apuração B'!$Q$2:$Q$21,"diverge")+COUNTIF('Apuração B'!$D$2:$D$21,"fonte insuficiente")*COUNTIF('Apuração B'!$Q$2:$Q$21,"fonte insuficiente")+COUNTIF('Apuração B'!$D$2:$D$21,"juízo discutível")*COUNTIF('Apuração B'!$Q$2:$Q$21,"juízo discutível"))/20^2)/(1-(COUNTIF('Apuração B'!$D$2:$D$21,"confere")*COUNTIF('Apuração B'!$Q$2:$Q$21,"confere")+COUNTIF('Apuração B'!$D$2:$D$21,"diverge")*COUNTIF('Apuração B'!$Q$2:$Q$21,"diverge")+COUNTIF('Apuração B'!$D$2:$D$21,"fonte insuficiente")*COUNTIF('Apuração B'!$Q$2:$Q$21,"fonte insuficiente")+COUNTIF('Apuração B'!$D$2:$D$21,"juízo discutível")*COUNTIF('Apuração B'!$Q$2:$Q$21,"juízo discutível"))/20^2)) | E27: =IF(D27>=0.8,"critério reproduzível",IF(D27>=0.6,"ler as discordâncias e escrever a regra","reconferir o campo nos 300"))
A28: tipo_pena | B28: 20 | C28: =SUMPRODUCT(--('Apuração B'!$R$2:$R$21='Apuração B'!$E$2:$E$21))/20 | D28: =IF((COUNTIF('Apuração B'!$E$2:$E$21,"confere")*COUNTIF('Apuração B'!$R$2:$R$21,"confere")+COUNTIF('Apuração B'!$E$2:$E$21,"diverge")*COUNTIF('Apuração B'!$R$2:$R$21,"diverge")+COUNTIF('Apuração B'!$E$2:$E$21,"fonte insuficiente")*COUNTIF('Apuração B'!$R$2:$R$21,"fonte insuficiente")+COUNTIF('Apuração B'!$E$2:$E$21,"juízo discutível")*COUNTIF('Apuração B'!$R$2:$R$21,"juízo discutível"))/20^2>=1,1,(SUMPRODUCT(--('Apuração B'!$R$2:$R$21='Apuração B'!$E$2:$E$21))/20-(COUNTIF('Apuração B'!$E$2:$E$21,"confere")*COUNTIF('Apuração B'!$R$2:$R$21,"confere")+COUNTIF('Apuração B'!$E$2:$E$21,"diverge")*COUNTIF('Apuração B'!$R$2:$R$21,"diverge")+COUNTIF('Apuração B'!$E$2:$E$21,"fonte insuficiente")*COUNTIF('Apuração B'!$R$2:$R$21,"fonte insuficiente")+COUNTIF('Apuração B'!$E$2:$E$21,"juízo discutível")*COUNTIF('Apuração B'!$R$2:$R$21,"juízo discutível"))/20^2)/(1-(COUNTIF('Apuração B'!$E$2:$E$21,"confere")*COUNTIF('Apuração B'!$R$2:$R$21,"confere")+COUNTIF('Apuração B'!$E$2:$E$21,"diverge")*COUNTIF('Apuração B'!$R$2:$R$21,"diverge")+COUNTIF('Apuração B'!$E$2:$E$21,"fonte insuficiente")*COUNTIF('Apuração B'!$R$2:$R$21,"fonte insuficiente")+COUNTIF('Apuração B'!$E$2:$E$21,"juízo discutível")*COUNTIF('Apuração B'!$R$2:$R$21,"juízo discutível"))/20^2)) | E28: =IF(D28>=0.8,"critério reproduzível",IF(D28>=0.6,"ler as discordâncias e escrever a regra","reconferir o campo nos 300"))
A29: hediondo | B29: 20 | C29: =SUMPRODUCT(--('Apuração B'!$S$2:$S$21='Apuração B'!$F$2:$F$21))/20 | D29: =IF((COUNTIF('Apuração B'!$F$2:$F$21,"confere")*COUNTIF('Apuração B'!$S$2:$S$21,"confere")+COUNTIF('Apuração B'!$F$2:$F$21,"diverge")*COUNTIF('Apuração B'!$S$2:$S$21,"diverge")+COUNTIF('Apuração B'!$F$2:$F$21,"fonte insuficiente")*COUNTIF('Apuração B'!$S$2:$S$21,"fonte insuficiente")+COUNTIF('Apuração B'!$F$2:$F$21,"juízo discutível")*COUNTIF('Apuração B'!$S$2:$S$21,"juízo discutível"))/20^2>=1,1,(SUMPRODUCT(--('Apuração B'!$S$2:$S$21='Apuração B'!$F$2:$F$21))/20-(COUNTIF('Apuração B'!$F$2:$F$21,"confere")*COUNTIF('Apuração B'!$S$2:$S$21,"confere")+COUNTIF('Apuração B'!$F$2:$F$21,"diverge")*COUNTIF('Apuração B'!$S$2:$S$21,"diverge")+COUNTIF('Apuração B'!$F$2:$F$21,"fonte insuficiente")*COUNTIF('Apuração B'!$S$2:$S$21,"fonte insuficiente")+COUNTIF('Apuração B'!$F$2:$F$21,"juízo discutível")*COUNTIF('Apuração B'!$S$2:$S$21,"juízo discutível"))/20^2)/(1-(COUNTIF('Apuração B'!$F$2:$F$21,"confere")*COUNTIF('Apuração B'!$S$2:$S$21,"confere")+COUNTIF('Apuração B'!$F$2:$F$21,"diverge")*COUNTIF('Apuração B'!$S$2:$S$21,"diverge")+COUNTIF('Apuração B'!$F$2:$F$21,"fonte insuficiente")*COUNTIF('Apuração B'!$S$2:$S$21,"fonte insuficiente")+COUNTIF('Apuração B'!$F$2:$F$21,"juízo discutível")*COUNTIF('Apuração B'!$S$2:$S$21,"juízo discutível"))/20^2)) | E29: =IF(D29>=0.8,"critério reproduzível",IF(D29>=0.6,"ler as discordâncias e escrever a regra","reconferir o campo nos 300"))
A30: violencia | B30: 20 | C30: =SUMPRODUCT(--('Apuração B'!$T$2:$T$21='Apuração B'!$G$2:$G$21))/20 | D30: =IF((COUNTIF('Apuração B'!$G$2:$G$21,"confere")*COUNTIF('Apuração B'!$T$2:$T$21,"confere")+COUNTIF('Apuração B'!$G$2:$G$21,"diverge")*COUNTIF('Apuração B'!$T$2:$T$21,"diverge")+COUNTIF('Apuração B'!$G$2:$G$21,"fonte insuficiente")*COUNTIF('Apuração B'!$T$2:$T$21,"fonte insuficiente")+COUNTIF('Apuração B'!$G$2:$G$21,"juízo discutível")*COUNTIF('Apuração B'!$T$2:$T$21,"juízo discutível"))/20^2>=1,1,(SUMPRODUCT(--('Apuração B'!$T$2:$T$21='Apuração B'!$G$2:$G$21))/20-(COUNTIF('Apuração B'!$G$2:$G$21,"confere")*COUNTIF('Apuração B'!$T$2:$T$21,"confere")+COUNTIF('Apuração B'!$G$2:$G$21,"diverge")*COUNTIF('Apuração B'!$T$2:$T$21,"diverge")+COUNTIF('Apuração B'!$G$2:$G$21,"fonte insuficiente")*COUNTIF('Apuração B'!$T$2:$T$21,"fonte insuficiente")+COUNTIF('Apuração B'!$G$2:$G$21,"juízo discutível")*COUNTIF('Apuração B'!$T$2:$T$21,"juízo discutível"))/20^2)/(1-(COUNTIF('Apuração B'!$G$2:$G$21,"confere")*COUNTIF('Apuração B'!$T$2:$T$21,"confere")+COUNTIF('Apuração B'!$G$2:$G$21,"diverge")*COUNTIF('Apuração B'!$T$2:$T$21,"diverge")+COUNTIF('Apuração B'!$G$2:$G$21,"fonte insuficiente")*COUNTIF('Apuração B'!$T$2:$T$21,"fonte insuficiente")+COUNTIF('Apuração B'!$G$2:$G$21,"juízo discutível")*COUNTIF('Apuração B'!$T$2:$T$21,"juízo discutível"))/20^2)) | E30: =IF(D30>=0.8,"critério reproduzível",IF(D30>=0.6,"ler as discordâncias e escrever a regra","reconferir o campo nos 300"))
A31: grave_ameaca | B31: 20 | C31: =SUMPRODUCT(--('Apuração B'!$U$2:$U$21='Apuração B'!$H$2:$H$21))/20 | D31: =IF((COUNTIF('Apuração B'!$H$2:$H$21,"confere")*COUNTIF('Apuração B'!$U$2:$U$21,"confere")+COUNTIF('Apuração B'!$H$2:$H$21,"diverge")*COUNTIF('Apuração B'!$U$2:$U$21,"diverge")+COUNTIF('Apuração B'!$H$2:$H$21,"fonte insuficiente")*COUNTIF('Apuração B'!$U$2:$U$21,"fonte insuficiente")+COUNTIF('Apuração B'!$H$2:$H$21,"juízo discutível")*COUNTIF('Apuração B'!$U$2:$U$21,"juízo discutível"))/20^2>=1,1,(SUMPRODUCT(--('Apuração B'!$U$2:$U$21='Apuração B'!$H$2:$H$21))/20-(COUNTIF('Apuração B'!$H$2:$H$21,"confere")*COUNTIF('Apuração B'!$U$2:$U$21,"confere")+COUNTIF('Apuração B'!$H$2:$H$21,"diverge")*COUNTIF('Apuração B'!$U$2:$U$21,"diverge")+COUNTIF('Apuração B'!$H$2:$H$21,"fonte insuficiente")*COUNTIF('Apuração B'!$U$2:$U$21,"fonte insuficiente")+COUNTIF('Apuração B'!$H$2:$H$21,"juízo discutível")*COUNTIF('Apuração B'!$U$2:$U$21,"juízo discutível"))/20^2)/(1-(COUNTIF('Apuração B'!$H$2:$H$21,"confere")*COUNTIF('Apuração B'!$U$2:$U$21,"confere")+COUNTIF('Apuração B'!$H$2:$H$21,"diverge")*COUNTIF('Apuração B'!$U$2:$U$21,"diverge")+COUNTIF('Apuração B'!$H$2:$H$21,"fonte insuficiente")*COUNTIF('Apuração B'!$U$2:$U$21,"fonte insuficiente")+COUNTIF('Apuração B'!$H$2:$H$21,"juízo discutível")*COUNTIF('Apuração B'!$U$2:$U$21,"juízo discutível"))/20^2)) | E31: =IF(D31>=0.8,"critério reproduzível",IF(D31>=0.6,"ler as discordâncias e escrever a regra","reconferir o campo nos 300"))
A32: elemento | B32: 20 | C32: =SUMPRODUCT(--('Apuração B'!$V$2:$V$21='Apuração B'!$I$2:$I$21))/20 | D32: =IF((COUNTIF('Apuração B'!$I$2:$I$21,"confere")*COUNTIF('Apuração B'!$V$2:$V$21,"confere")+COUNTIF('Apuração B'!$I$2:$I$21,"diverge")*COUNTIF('Apuração B'!$V$2:$V$21,"diverge")+COUNTIF('Apuração B'!$I$2:$I$21,"fonte insuficiente")*COUNTIF('Apuração B'!$V$2:$V$21,"fonte insuficiente")+COUNTIF('Apuração B'!$I$2:$I$21,"juízo discutível")*COUNTIF('Apuração B'!$V$2:$V$21,"juízo discutível"))/20^2>=1,1,(SUMPRODUCT(--('Apuração B'!$V$2:$V$21='Apuração B'!$I$2:$I$21))/20-(COUNTIF('Apuração B'!$I$2:$I$21,"confere")*COUNTIF('Apuração B'!$V$2:$V$21,"confere")+COUNTIF('Apuração B'!$I$2:$I$21,"diverge")*COUNTIF('Apuração B'!$V$2:$V$21,"diverge")+COUNTIF('Apuração B'!$I$2:$I$21,"fonte insuficiente")*COUNTIF('Apuração B'!$V$2:$V$21,"fonte insuficiente")+COUNTIF('Apuração B'!$I$2:$I$21,"juízo discutível")*COUNTIF('Apuração B'!$V$2:$V$21,"juízo discutível"))/20^2)/(1-(COUNTIF('Apuração B'!$I$2:$I$21,"confere")*COUNTIF('Apuração B'!$V$2:$V$21,"confere")+COUNTIF('Apuração B'!$I$2:$I$21,"diverge")*COUNTIF('Apuração B'!$V$2:$V$21,"diverge")+COUNTIF('Apuração B'!$I$2:$I$21,"fonte insuficiente")*COUNTIF('Apuração B'!$V$2:$V$21,"fonte insuficiente")+COUNTIF('Apuração B'!$I$2:$I$21,"juízo discutível")*COUNTIF('Apuração B'!$V$2:$V$21,"juízo discutível"))/20^2)) | E32: =IF(D32>=0.8,"critério reproduzível",IF(D32>=0.6,"ler as discordâncias e escrever a regra","reconferir o campo nos 300"))
A33: tentativa | B33: 20 | C33: =SUMPRODUCT(--('Apuração B'!$W$2:$W$21='Apuração B'!$J$2:$J$21))/20 | D33: =IF((COUNTIF('Apuração B'!$J$2:$J$21,"confere")*COUNTIF('Apuração B'!$W$2:$W$21,"confere")+COUNTIF('Apuração B'!$J$2:$J$21,"diverge")*COUNTIF('Apuração B'!$W$2:$W$21,"diverge")+COUNTIF('Apuração B'!$J$2:$J$21,"fonte insuficiente")*COUNTIF('Apuração B'!$W$2:$W$21,"fonte insuficiente")+COUNTIF('Apuração B'!$J$2:$J$21,"juízo discutível")*COUNTIF('Apuração B'!$W$2:$W$21,"juízo discutível"))/20^2>=1,1,(SUMPRODUCT(--('Apuração B'!$W$2:$W$21='Apuração B'!$J$2:$J$21))/20-(COUNTIF('Apuração B'!$J$2:$J$21,"confere")*COUNTIF('Apuração B'!$W$2:$W$21,"confere")+COUNTIF('Apuração B'!$J$2:$J$21,"diverge")*COUNTIF('Apuração B'!$W$2:$W$21,"diverge")+COUNTIF('Apuração B'!$J$2:$J$21,"fonte insuficiente")*COUNTIF('Apuração B'!$W$2:$W$21,"fonte insuficiente")+COUNTIF('Apuração B'!$J$2:$J$21,"juízo discutível")*COUNTIF('Apuração B'!$W$2:$W$21,"juízo discutível"))/20^2)/(1-(COUNTIF('Apuração B'!$J$2:$J$21,"confere")*COUNTIF('Apuração B'!$W$2:$W$21,"confere")+COUNTIF('Apuração B'!$J$2:$J$21,"diverge")*COUNTIF('Apuração B'!$W$2:$W$21,"diverge")+COUNTIF('Apuração B'!$J$2:$J$21,"fonte insuficiente")*COUNTIF('Apuração B'!$W$2:$W$21,"fonte insuficiente")+COUNTIF('Apuração B'!$J$2:$J$21,"juízo discutível")*COUNTIF('Apuração B'!$W$2:$W$21,"juízo discutível"))/20^2)) | E33: =IF(D33>=0.8,"critério reproduzível",IF(D33>=0.6,"ler as discordâncias e escrever a regra","reconferir o campo nos 300"))
A34: acao | B34: 20 | C34: =SUMPRODUCT(--('Apuração B'!$X$2:$X$21='Apuração B'!$K$2:$K$21))/20 | D34: =IF((COUNTIF('Apuração B'!$K$2:$K$21,"confere")*COUNTIF('Apuração B'!$X$2:$X$21,"confere")+COUNTIF('Apuração B'!$K$2:$K$21,"diverge")*COUNTIF('Apuração B'!$X$2:$X$21,"diverge")+COUNTIF('Apuração B'!$K$2:$K$21,"fonte insuficiente")*COUNTIF('Apuração B'!$X$2:$X$21,"fonte insuficiente")+COUNTIF('Apuração B'!$K$2:$K$21,"juízo discutível")*COUNTIF('Apuração B'!$X$2:$X$21,"juízo discutível"))/20^2>=1,1,(SUMPRODUCT(--('Apuração B'!$X$2:$X$21='Apuração B'!$K$2:$K$21))/20-(COUNTIF('Apuração B'!$K$2:$K$21,"confere")*COUNTIF('Apuração B'!$X$2:$X$21,"confere")+COUNTIF('Apuração B'!$K$2:$K$21,"diverge")*COUNTIF('Apuração B'!$X$2:$X$21,"diverge")+COUNTIF('Apuração B'!$K$2:$K$21,"fonte insuficiente")*COUNTIF('Apuração B'!$X$2:$X$21,"fonte insuficiente")+COUNTIF('Apuração B'!$K$2:$K$21,"juízo discutível")*COUNTIF('Apuração B'!$X$2:$X$21,"juízo discutível"))/20^2)/(1-(COUNTIF('Apuração B'!$K$2:$K$21,"confere")*COUNTIF('Apuração B'!$X$2:$X$21,"confere")+COUNTIF('Apuração B'!$K$2:$K$21,"diverge")*COUNTIF('Apuração B'!$X$2:$X$21,"diverge")+COUNTIF('Apuração B'!$K$2:$K$21,"fonte insuficiente")*COUNTIF('Apuração B'!$X$2:$X$21,"fonte insuficiente")+COUNTIF('Apuração B'!$K$2:$K$21,"juízo discutível")*COUNTIF('Apuração B'!$X$2:$X$21,"juízo discutível"))/20^2)) | E34: =IF(D34>=0.8,"critério reproduzível",IF(D34>=0.6,"ler as discordâncias e escrever a regra","reconferir o campo nos 300"))
A36: Campo de prevalência extrema (hediondez, ~9%) pode ter κ baixo com concordância alta: leia as duas medidas (AUDITORIA.md, seção 7).

Sheet Gabarito
A1: id | B1: pena_min | C1: pena_max | D1: tipo_pena | E1: hediondo | F1: violencia | G1: grave_ameaca | H1: elemento | I1: tentativa | J1: acao | K1: nome | L1: vigente | M1: estrato | N1: dupla
A2: 165 | B2: 12 | C2: 36 | D2: Reclusão | E2: Não | F2: Não | G2: Não | H2: Doloso | I2: Sim | J2: Pública Incondicionada | K2: Destruição, subtração ou ocultação de cadáver | L2: Sim | M2: h1 | N2: sim
A3: 1335 | B3: 6 | C3: 24 | D3: Detenção | E3: Não | F3: Não | G3: Não | H3: Culposo | I3: Não | J3: Pública Incondicionada | K3: Inundação — modalidade culposa | L3: Sim | M3: h1 | N3: sim
A4: 172 | B4: 24 | C4: 72 | D4: Reclusão | E4: Não | F4: Não | G4: Não | H4: Doloso | I4: Sim | J4: Pública Incondicionada | K4: Bigamia | L4: Sim | M4: h1 | N4: sim
A5: 994 | B5: 6 | C5: 36 | D5: Detenção | E5: Não | F5: Não | G5: Não | H5: Doloso | I5: Sim | J5: Pública Incondicionada | K5: Alteração de marca ou sinal indicativo de propriedade de gado ou rebanho | L5: Sim | M5: h1 | N5: sim
A6: 70 | B6: 24 | C6: 60 | D6: Reclusão | E6: Não | F6: Não | G6: Não | H6: Doloso | I6: Sim | J6: Pública Incondicionada | K6: Sequestro qualificado (fins libidinosos, menor de 18, maus-tratos, mais de 15 dias) | L6: Sim | M6: h1 | N6: sim
A7: 66 | B7: 1 | C7: 6 | D7: Detenção | E7: Não | F7: Não | G7: Sim | H7: Doloso | I7: Sim | J7: Pública Condicionada à Representação | K7: Ameaça | L7: Sim | M7: h1 | N7: sim
A8: 280 | B8: 24 | C8: 48 | D8: Reclusão | E8: Não | F8: Não | G8: Não | H8: Doloso | I8: Sim | J8: Pública Incondicionada | K8: Falso testemunho ou falsa perícia | L8: Sim | M8: h1
A9: 231 | B9: 24 | C9: 72 | D9: Reclusão | E9: Não | F9: Não | G9: Não | H9: Doloso | I9: Sim | J9: Pública Incondicionada | K9: Falsificação de documento público | L9: Sim | M9: h1
A10: 1379 | B10: 0.5 | C10: 3 | D10: Detenção | E10: Não | F10: Não | G10: Não | H10: Doloso | I10: Sim | J10: Pública Incondicionada | K10: Favorecimento pessoal — Se ao crime não é cominada pena de reclusão | L10: Sim | M10: h1
A11: 153 | B11: 1 | C11: 12 | D11: Detenção | E11: Não | F11: Sim | G11: Sim | H11: Doloso | I11: Sim | J11: Pública Incondicionada | K11: Atentado contra a liberdade de associação | L11: Sim | M11: h1
A12: 275 | B12: 12 | C12: 96 | D12: Reclusão | E12: Não | F12: Não | G12: Não | H12: Doloso | I12: Sim | J12: Pública Incondicionada | K12: Corrupção ativa em transação comercial internacional | L12: Sim | M12: h1
A13: 1375 | B13: 12 | C13: 36 | D13: Reclusão | E13: Não | F13: Não | G13: Não | H13: Doloso | I13: Sim | J13: Pública Incondicionada | K13: Contratação inidônea | L13: Sim | M13: h1
A14: 186 | B14: 6 | C14: 24 | D14: Detenção | E14: Não | F14: Não | G14: Não | H14: Culposo | I14: Não | J14: Pública Incondicionada | K14: Incêndio culposo | L14: Sim | M14: h1
A15: 49 | B15: 96 | C15: 168 | D15: Reclusão | E15: Não | F15: Não | G15: Não | H15: Preterdoloso | I15: Não | J15: Pública Incondicionada | K15: Abandono de incapaz com resultado morte | L15: Sim | M15: h1
A16: 213 | B16: 12 | C16: 36 | D16: Detenção | E16: Não | F16: Não | G16: Não | H16: Doloso | I16: Sim | J16: Pública Incondicionada | K16: Outras substâncias nocivas à saúde pública | L16: Sim | M16: h1
A17: 151 | B17: 1 | C17: 12 | D17: Detenção | E17: Não | F17: Sim | G17: Sim | H17: Doloso | I17: Sim | J17: Pública Incondicionada | K17: Atentado contra a liberdade de trabalho — profissão ou trabalho | L17: Sim | M17: h1
A18: 1338 | B18: 12 | C18: 36 | D18: Detenção | E18: Não | F18: Não | G18: Não | H18: Preterdoloso | I18: Não | J18: Pública Incondicionada | K18: Exposição ou abandono de recém-nascido — lesão grave | L18: Sim | M18: h1
A19: 294 | B19: 6 | C19: 36 | D19: Detenção | E19: Não | F19: Não | G19: Não | H19: Doloso | I19: Sim | J19: Pública Incondicionada | K19: Sonegação de papel ou objeto de valor probatório por advogado ou procurador | L19: Sim | M19: h1
... A35: 12 | B35: 16 | C35: 48 | D35: Detenção | E35: Não | F35: Não | G35: Não | H35: Culposo | I35: Não | J35: Pública Incondicionada | K35: Homicídio culposo com aumento de 1/3 (inobservância de regra técnica) | L35: Sim | M35: h2
A36: 706 | B36: 6 | C36: 24 | D36: Detenção | E36: Não | F36: Não | G36: Não | H36: Doloso | I36: Sim | J36: Pública Incondicionada | K36: Receita ilegal | L36: Sim | M36: h3 | N36: sim
A37: 1196 | B37: 6 | C37: 24 | D37: Detenção | E37: Não | F37: Não | G37: Não | H37: Doloso | I37: Sim | J37: Pública Incondicionada | K37: Violação de sigilo funcional | L37: Sim | M37: h3 | N37: sim
A38: 1108 | B38: 6 | C38: 12 | D38: Detenção | E38: Não | F38: Não | G38: Não | H38: Doloso | I38: Sim | J38: Pública Incondicionada | K38: Ato de libidinagem | L38: Sim | M38: h3 | N38: sim
A39: 1050 | B39: 1 | C39: 6 | D39: Detenção | E39: Não | F39: Não | G39: Não | H39: Doloso | I39: Sim | J39: Pública Incondicionada | K39: Uso indevido de uniforme, distintivo ou insígnia militar por qualquer pessoa | L39: Sim | M39: h3 | N39: sim
A40: 1383 | B40: 12 | C40: 36 | D40: Reclusão | E40: Não | F40: Não | G40: Não | H40: Doloso | I40: Sim | J40: Pública Incondicionada | K40: Amotinamento (cabeça) | L40: Sim | M40: h3
A41: 1026 | B41: 120 | C41: 240 | D41: Reclusão | E41: Não | F41: Não | G41: Não | H41: Doloso | I41: Sim | J41: Pública Incondicionada | K41: Turbação de objeto ou documento — comprometimento da segurança ou eficiência bélica | L41: Sim | M41: h3
A42: 1084 | B42: 2 | C42: 12 | D42: Detenção | E42: Não | F42: Não | G42: Não | H42: Culposo | I42: Não | J42: Pública Incondicionada | K42: Lesão culposa | L42: Sim | M42: h3
A43: 1033 | B43: 36 | C43: 60 | D43: Reclusão | E43: Não | F43: Não | G43: Não | H43: Doloso | I43: Sim | J43: Pública Incondicionada | K43: Omissão de lealdade militar | L43: Sim | M43: h3
A44: 1182 | B44: 24 | C44: 48 | D44: Reclusão | E44: Não | F44: Não | G44: Não | H44: Doloso | I44: Sim | J44: Pública Incondicionada | K44: Participação ilícita | L44: Sim | M44: h3
A45: 1273 | B45: 12 | C45: 72 | D45: Detenção | E45: Não | F45: Não | G45: Não | H45: Doloso | I45: Sim | J45: Pública Incondicionada | K45: Falta de apresentação | L45: Sim | M45: h3
A46: 702 | B46: 12 | C46: 72 | D46: Reclusão | E46: Não | F46: Não | G46: Não | H46: Doloso | I46: Sim | J46: Pública Incondicionada | K46: Apropriação indébita simples | L46: Sim | M46: h3
A47: 1121 | B47: 12 | C47: 60 | D47: Reclusão | E47: Não | F47: Não | G47: Não | H47: Doloso | I47: Sim | J47: Pública Incondicionada | K47: Receptação | L47: Sim | M47: h3
A48: 710 | B48: 12 | C48: 96 | D48: Reclusão | E48: Não | F48: Não | G48: Não | H48: Doloso | I48: Sim | J48: Pública Incondicionada | K48: Corrupção ativa | L48: Sim | M48: h3
A49: 707 | B49: 12 | C49: 48 | D49: Reclusão | E49: Não | F49: Não | G49: Não | H49: Doloso | I49: Sim | J49: Pública Incondicionada | K49: Desacato a superior | L49: Sim | M49: h3
A50: 1269 | B50: 180 | C50: 360 | D50: Morte | E50: Não | F50: Sim | G50: Não | H50: Doloso | I50: Sim | J50: Pública Incondicionada | K50: Violência contra superior ou militar de serviço — com arma, em presença do inimigo | L50: Sim | M50: h3
A51: 1070 | B51: 24 | C51: 48 | D51: Reclusão | E51: Não | F51: Não | G51: Não | H51: Doloso | I51: Sim | J51: Pública Incondicionada | K51: Concêrto para deserção | L51: Sim | M51: h3
... A55: 675 | B55: 96 | C55: 180 | D55: Reclusão | E55: Não | F55: Não | G55: Não | H55: Doloso | I55: Sim | J55: Pública Incondicionada | K55: Hostilidade contra país estrangeiro | L55: Sim | M55: h3
A56: 1437 | B56: 48 | C56: 144 | D56: Reclusão | E56: Não | F56: Não | G56: Não | H56: Doloso | I56: Sim | J56: Pública Incondicionada | K56: Furto qualificado — coisa pertencente à Fazenda Pública (tempo de guerra) | L56: Sim | M56: h4 | N56: sim
A57: 1445 | B57: 128 | C57: 360 | D57: Reclusão | E57: Não | F57: Sim | G57: Sim | H57: Doloso | I57: Sim | J57: Pública Incondicionada | K57: Extorsão qualificada (tempo de guerra) | L57: Sim | M57: h4
A58: 1439 | B58: 72 | C58: 240 | D58: Reclusão | E58: Não | F58: Não | G58: Não | H58: Doloso | I58: Sim | J58: Pública Incondicionada | K58: Furto qualificado — material de uso restrito militar (tempo de guerra) | L58: Sim | M58: h4
A59: 1435 | B59: 9 | C59: 36 | D59: Detenção | E59: Não | F59: Não | G59: Não | H59: Doloso | I59: Sim | J59: Pública Incondicionada | K59: Deserção por evasão ou fuga (tempo de guerra) | L59: Sim | M59: h4
A60: 1433 | B60: 4.5 | C60: 18 | D60: Detenção | E60: Não | F60: Não | G60: Não | H60: Doloso | I60: Sim | J60: Pública Incondicionada | K60: Concerto para deserção não consumada (tempo de guerra) | L60: Sim | M60: h4
A61: 1526 | B61: 96 | C61: 240 | D61: Reclusão | E61: Sim | F61: Não | G61: Sim | H61: Qualificado pelo resultado | I61: Sim | J61: Pública Incondicionada | K61: Extorsão mediante sequestro — grave sofrimento físico ou moral (tempo de paz) | L61: Sim | M61: h4
A62: 1431 | B62: 4.5 | C62: 18 | D62: Detenção | E62: Não | F62: Não | G62: Não | H62: Doloso | I62: Sim | J62: Pública Incondicionada | K62: Deserção especial — apresentação em mais de 5 e até 8 dias (tempo de guerra) | L62: Sim | M62: h4
A63: 1454 | B63: 180 | C63: 360 | D63: Reclusão | E63: Sim | F63: Sim | G63: Sim | H63: Qualificado pelo resultado | I63: Sim | J63: Pública Incondicionada | K63: Extorsão qualificada pela morte (tempo de paz) | L63: Sim | M63: h4
A64: 1527 | B64: 120 | C64: 360 | D64: Reclusão | E64: Sim | F64: Não | G64: Não | H64: Preterdoloso | I64: Não | J64: Pública Incondicionada | K64: Epidemia com resultado morte | L64: Sim | M64: h4
A65: 1429 | B65: 1.5 | C65: 4.5 | D65: Detenção | E65: Não | F65: Não | G65: Não | H65: Doloso | I65: Sim | J65: Pública Incondicionada | K65: Deserção especial (tempo de guerra) | L65: Sim | M65: h4
A66: 1430 | B66: 3 | C66: 12 | D66: Detenção | E66: Não | F66: Não | G66: Não | H66: Doloso | I66: Sim | J66: Pública Incondicionada | K66: Deserção especial — apresentação em mais de 24 horas e até 5 dias (tempo de guerra) | L66: Sim | M66: h4
A67: 1298 | B67: 6 | C67: 24 | D67: Detenção | E67: Não | F67: Não | G67: Não | H67: Doloso | I67: Não | J67: Pública Incondicionada | K67: Usura real | L67: Sim | M67: h5 | N67: sim
A68: 941 | B68: 3 | C68: 6 | D68: Detenção | E68: Não | F68: Não | G68: Não | H68: Doloso | I68: Não | J68: Pública Incondicionada | K68: Propaganda eleitoral em língua estrangeira | L68: Sim | M68: h5 | N68: sim
A69: 786 | B69: 6 | C69: 24 | D69: Detenção | E69: Não | F69: Não | G69: Não | H69: Doloso | I69: Sim | J69: Pública Incondicionada | K69: Calúnia eleitoral | L69: Sim | M69: h5 | N69: sim
A70: 660 | B70: 24 | C70: 60 | D70: Reclusão | E70: Não | F70: Não | G70: Não | H70: Doloso | I70: Sim | J70: Pública Incondicionada | K70: Supressão ou redução de tributo — fraude à fiscalização tributária | L70: Sim | M70: h5 | N70: sim
A71: 884 | B71: 0 | C71: 6 | D71: Detenção | E71: Não | F71: Não | G71: Não | H71: Doloso | I71: Sim | J71: Pública Incondicionada | K71: Violação de correspondência | L71: Sim | M71: h5 | N71: sim
A72: 846 | B72: 1 | C72: 6 | D72: Prisão simples | E72: Não | F72: Não | G72: Não | H72: Doloso | I72: Não | J72: Pública Incondicionada | K72: Impressão de bilhetes, listas de sorteio, avisos ou cartazes de loteria onde ela não possa legalmente circular | L72: Sim | M72: h5 | N72: sim
A73: 433 | B73: 12 | C73: 48 | D73: Detenção | E73: Não | F73: Não | G73: Não | H73: Doloso | I73: Não | J73: Pública Incondicionada | K73: Manutenção de presos de sexos diferentes na mesma cela ou espaço de confinamento | L73: Sim | M73: h5 | N73: sim
A74: 395 | B74: 24 | C74: 60 | D74: Reclusão | E74: Não | F74: Não | G74: Não | H74: Doloso | I74: Sim | J74: Pública Incondicionada | K74: Sonegação fiscal material (suprimir/reduzir tributo mediante conduta comissiva) | L74: Sim | M74: h5
A75: 645 | B75: 12 | C75: 48 | D75: Reclusão | E75: Não | F75: Não | G75: Não | H75: Doloso | I75: Sim | J75: Pública Incondicionada | K75: Engenharia genética em célula germinal humana, zigoto ou embrião humano | L75: Sim | M75: h5
A76: 914 | B76: 1 | C76: 4 | D76: Prisão simples | E76: Não | F76: Não | G76: Não | H76: Doloso | I76: Não | J76: Pública Incondicionada | K76: Exibição ou guarda de listas de sorteio de loteria estrangeira ou de loteria estadual fora do território respectivo | L76: Sim | M76: h5
A77: 844 | B77: 2 | C77: 6 | D77: Prisão simples | E77: Não | F77: Não | G77: Não | H77: Doloso | I77: Não | J77: Pública Incondicionada | K77: Loteria estadual | L77: Sim | M77: h5
A78: 1007 | B78: 6 | C78: 24 | D78: Detenção | E78: Não | F78: Não | G78: Não | H78: Doloso | I78: Sim | J78: Pública Incondicionada | K78: Usura pecuniária (cobrar juros, comissões ou descontos acima da taxa legal) | L78: Sim | M78: h5
A79: 391 | B79: 6 | C79: 24 | D79: Reclusão | E79: Não | F79: Não | G79: Não | H79: Doloso | I79: Sim | J79: Pública Incondicionada | K79: Recusa ou omissão de dados requisitados na investigação ou no processo | L79: Sim | M79: h5
A80: 967 | B80: 12 | C80: 36 | D80: Detenção | E80: Não | F80: Não | G80: Não | H80: Doloso | I80: Sim | J80: Pública Incondicionada | K80: Exibição de informações ou imagens depreciativas da pessoa idosa | L80: Sim | M80: h5
A81: 1005 | B81: 6 | C81: 24 | D81: Detenção | E81: Não | F81: Não | G81: Não | H81: Doloso | I81: Sim | J81: Pública Incondicionada | K81: Negativa de acesso aos autos ao interessado, ao defensor ou ao advogado | L81: Sim | M81: h5
A82: 420 | B82: 12 | C82: 36 | D82: Reclusão | E82: Não | F82: Não | G82: Não | H82: Doloso | I82: Sim | J82: Pública Incondicionada | K82: Impedimento de acesso ou uso de transportes públicos | L82: Sim | M82: h5
A83: 1427 | B83: 3 | C83: 12 | D83: Detenção | E83: Não | F83: Não | G83: Não | H83: Culposo | I83: Não | J83: Pública Incondicionada | K83: Descumprimento de obrigação de relevante interesse ambiental — modalidade culposa | L83: Sim | M83: h5
A84: 362 | B84: 12 | C84: 24 | D84: Reclusão | E84: Não | F84: Não | G84: Não | H84: Doloso | I84: Sim | J84: Pública Incondicionada | K84: Cortar ou transformar em carvão madeira de lei protegida sem autorização | L84: Sim | M84: h5
A85: 532 | B85: 6 | C85: 12 | D85: Detenção | E85: Não | F85: Não | G85: Não | H85: Doloso | I85: Sim | J85: Pública Incondicionada | K85: Divulgação de pesquisa eleitoral fraudulenta | L85: Sim | M85: h5
... A89: 487 | B89: 24 | C89: 48 | D89: Reclusão | E89: Não | F89: Não | G89: Não | H89: Doloso | I89: Sim | J89: Pública Incondicionada | K89: Apresentação de relação ou habilitação de créditos falsa em falência ou recuperação | L89: Sim | M89: h5
A90: 547 | B90: 2 | C90: 24 | D90: Detenção | E90: Não | F90: Não | G90: Não | H90: Doloso | I90: Sim | J90: Pública Incondicionada | K90: Impedimento ou tentativa de impedimento de funcionamento de CPI | L90: Sim | M90: h6 | N90: sim
A91: 1320 | B91: 48 | C91: 96 | D91: Reclusão | E91: Sim | F91: Não | G91: Não | H91: Doloso | I91: Sim | J91: Pública Incondicionada | K91: Agenciamento, recrutamento ou intermediação da participação de criança ou adolescente em cena de sexo explícito | L91: Sim | M91: h6 | N91: sim
A92: 919 | B92: 12 | C92: 60 | D92: Reclusão | E92: Não | F92: Não | G92: Não | H92: Doloso | I92: Não | J92: Pública Incondicionada | K92: Falsificação, emenda ou adulteração de bilhete de loteria | L92: Sim | M92: h6
A93: 394 | B93: 12 | C93: 80 | D93: Reclusão | E93: Não | F93: Não | G93: Não | H93: Doloso | I93: Sim | J93: Pública Incondicionada | K93: Lavagem de dinheiro com diminuição de 1/3 a 2/3 (colaboração espontânea) | L93: Sim | M93: h6
A94: 952 | B94: 0 | C94: 0 | D94: — | E94: Não | F94: Não | G94: Não | H94: Doloso | I94: Não | J94: Pública Incondicionada | K94: Obtenção de documento falso para fins eleitorais | L94: Sim | M94: h6
A95: 1473 | B95: 24 | C95: 96 | D95: Reclusão | E95: Sim | F95: Não | G95: Não | H95: Doloso | I95: Sim | J95: Pública Incondicionada | K95: Incitação ao genocídio com crime consumado — lesão grave a membros do grupo | L95: Sim | M95: h6
A96: 1469 | B96: 60 | C96: 90 | D96: Reclusão | E96: Sim | F96: Não | G96: Não | H96: Doloso | I96: Sim | J96: Pública Incondicionada | K96: Incitação ao genocídio — condições de existência destrutivas | L96: Sim | M96: h6
A97: 829 | B97: 0 | C97: 0 | D97: Multa | E97: Não | F97: Não | G97: Não | H97: Doloso | I97: Não | J97: Pública Incondicionada | K97: Perigo de desabamento | L97: Sim | M97: h6
A98: 1326 | B98: 12 | C98: 36 | D98: Reclusão | E98: Não | F98: Sim | G98: Não | H98: Doloso | I98: Sim | J98: Pública Incondicionada | K98: Obstrução ou violência contra manifestações ou práticas religiosas | L98: Sim | M98: h6
A99: 904 | B99: 3 | C99: 36 | D99: Detenção | E99: Não | F99: Não | G99: Não | H99: Doloso | I99: Sim | J99: Pública Incondicionada | K99: Crime de responsabilidade de prefeito — demais condutas (itens III a XXIII): desvio de verba, contratação irregular, negativa de execução de lei, entre outras | L99: Sim | M99: h6
A100: 1321 | B100: 48 | C100: 96 | D100: Reclusão | E100: Sim | F100: Não | G100: Não | H100: Doloso | I100: Sim | J100: Pública Incondicionada | K100: Exibição ou transmissão em tempo real, pela internet ou meio digital, de cena de sexo explícito com criança ou adolescente | L100: Sim | M100: h6
A101: 1530 | B101: 0 | C101: 6 | D101: Detenção | E101: Não | F101: Não | G101: Não | H101: Doloso | I101: Sim | J101: Pública Incondicionada | K101: Sonegação ou destruição de correspondência | L101: Sim | M101: h6
